{"sessionDate":"20.10.17","sessionName":"XXVIII сесія VII скликання","voting":[{"voteName":"Про обрання секретаря сесії","namedVoting":[{"1016":"НЕ ГОЛОСУВАВ"},{"1023":"ЗА"},{"1031":"ЗА"},{"1033":"НЕ ГОЛОСУВАВ"},{"1012":"ЗА"},{"1013":"ЗА"},{"1037":"ЗА"},{"1022":"НЕ ГОЛОСУВАВ"},{"1004":"ЗА"},{"1028":"НЕ ГОЛОСУВАВ"},{"1032":"ЗА"},{"1029":"ЗА"},{"1015":"ЗА"},{"1009":"ЗА"},{"1006":"ЗА"},{"1025":"НЕ ГОЛОСУВАВ"},{"1030":"НЕ ГОЛОСУВАВ"},{"1034":"ЗА"},{"1017":"ЗА"},{"1035":"ЗА"},{"1003":"ЗА"},{"1026":"ЗА"},{"1010":"ЗА"},{"1018":"НЕ ГОЛОСУВАВ"},{"1001":"ЗА"},{"1019":"ЗА"},{"1007":"ЗА"},{"1011":"ВІДСУТНІЙ"},{"1020":"ЗА"},{"1005":"ЗА"},{"1021":"УТРИМАВСЯ"},{"1024":"ЗА"},{"1002":"ЗА"},{"1027":"НЕ ГОЛОСУВАВ"},{"1014":"ЗА"},{"1036":"ЗА"}],"voteTimestamp":"20.10.17 10:22:05"},{"voteName":"Про обрання лічильної комісії","namedVoting":[{"1016":"НЕ ГОЛОСУВАВ"},{"1023":"ЗА"},{"1031":"ЗА"},{"1033":"НЕ ГОЛОСУВАВ"},{"1012":"ЗА"},{"1013":"ЗА"},{"1037":"ЗА"},{"1022":"НЕ ГОЛОСУВАВ"},{"1004":"ЗА"},{"1028":"ЗА"},{"1032":"ЗА"},{"1029":"ЗА"},{"1015":"НЕ ГОЛОСУВАВ"},{"1009":"ЗА"},{"1006":"ЗА"},{"1025":"НЕ ГОЛОСУВАВ"},{"1030":"ЗА"},{"1034":"ЗА"},{"1017":"ЗА"},{"1035":"ЗА"},{"1003":"ЗА"},{"1026":"ЗА"},{"1010":"ЗА"},{"1018":"НЕ ГОЛОСУВАВ"},{"1001":"ЗА"},{"1019":"ЗА"},{"1007":"ЗА"},{"1011":"ЗА"},{"1020":"ЗА"},{"1005":"ЗА"},{"1021":"ЗА"},{"1024":"ЗА"},{"1002":"ЗА"},{"1027":"ЗА"},{"1014":"ЗА"},{"1036":"ЗА"}],"voteTimestamp":"20.10.17 10:22:58"},{"voteName":"Про затвердження порядку денного ХХVІІІ сесії Дрогобицької міської ради","namedVoting":[{"1016":"ЗА"},{"1023":"ЗА"},{"1031":"ЗА"},{"1033":"НЕ ГОЛОСУВАВ"},{"1012":"ЗА"},{"1013":"ЗА"},{"1037":"ЗА"},{"1022":"НЕ ГОЛОСУВАВ"},{"1004":"ЗА"},{"1028":"ЗА"},{"1032":"ЗА"},{"1029":"ЗА"},{"1015":"ЗА"},{"1009":"ЗА"},{"1006":"ЗА"},{"1025":"НЕ ГОЛОСУВАВ"},{"1030":"ЗА"},{"1034":"ЗА"},{"1017":"ЗА"},{"1035":"ЗА"},{"1003":"ЗА"},{"1026":"ЗА"},{"1010":"ЗА"},{"1018":"НЕ ГОЛОСУВАВ"},{"1001":"ЗА"},{"1019":"ЗА"},{"1007":"ЗА"},{"1011":"ЗА"},{"1020":"ЗА"},{"1005":"ЗА"},{"1021":"ЗА"},{"1024":"ЗА"},{"1002":"ЗА"},{"1027":"ЗА"},{"1014":"ЗА"},{"1036":"ЗА"}],"voteTimestamp":"20.10.17 10:23:34"},{"voteName":"пропозиція: включити до порядку денного питання Про внесення змін в кількісний та персональний склад виконавчого комітету Дрогобицької міської ради","namedVoting":[{"1016":"ЗА"},{"1023":"ЗА"},{"1031":"ЗА"},{"1033":"НЕ ГОЛОСУВАВ"},{"1012":"НЕ ГОЛОСУВАВ"},{"1013":"ЗА"},{"1037":"ЗА"},{"1022":"НЕ ГОЛОСУВАВ"},{"1004":"ЗА"},{"1028":"ЗА"},{"1032":"ЗА"},{"1029":"ЗА"},{"1015":"ЗА"},{"1009":"ЗА"},{"1006":"ЗА"},{"1025":"НЕ ГОЛОСУВАВ"},{"1030":"ЗА"},{"1034":"ЗА"},{"1017":"ЗА"},{"1035":"ЗА"},{"1003":"ЗА"},{"1026":"ЗА"},{"1010":"ЗА"},{"1018":"НЕ ГОЛОСУВАВ"},{"1001":"ЗА"},{"1019":"ЗА"},{"1007":"ЗА"},{"1011":"ЗА"},{"1020":"ЗА"},{"1005":"ЗА"},{"1021":"ЗА"},{"1024":"ЗА"},{"1002":"НЕ ГОЛОСУВАВ"},{"1027":"ЗА"},{"1014":"ЗА"},{"1036":"ЗА"}],"voteTimestamp":"20.10.17 10:24:30"},{"voteName":"зняти з розгляду питання Про внесення змін у п.п. 1, 2 додатку до рішення сесії Дрогобицької міської ради № 680 від 06.04.2017 р. Про включення в перелік об\u2019єктів комунальної власності, що підлягають приватизації шляхом викупу\u201D та п.п. 4, 5 додатку до рішення сесії Дрогобицької міської ради  № 811 від 30.08.2017 р. Про затвердження експертних оцінок об\u2019єктів комунальної власності Дрогобицької міської ради, які приватизовуються шляхом викупу\u201D","namedVoting":[{"1016":"ЗА"},{"1023":"ЗА"},{"1031":"ЗА"},{"1033":"НЕ ГОЛОСУВАВ"},{"1012":"НЕ ГОЛОСУВАВ"},{"1013":"ЗА"},{"1037":"ЗА"},{"1022":"НЕ ГОЛОСУВАВ"},{"1004":"ЗА"},{"1028":"ЗА"},{"1032":"ЗА"},{"1029":"ЗА"},{"1015":"ЗА"},{"1009":"ЗА"},{"1006":"ЗА"},{"1025":"НЕ ГОЛОСУВАВ"},{"1030":"ЗА"},{"1034":"ЗА"},{"1017":"НЕ ГОЛОСУВАВ"},{"1035":"ЗА"},{"1003":"ЗА"},{"1026":"ЗА"},{"1010":"ЗА"},{"1018":"НЕ ГОЛОСУВАВ"},{"1001":"ЗА"},{"1019":"ЗА"},{"1007":"ЗА"},{"1011":"ЗА"},{"1020":"ЗА"},{"1005":"ЗА"},{"1021":"ЗА"},{"1024":"ЗА"},{"1002":"НЕ ГОЛОСУВАВ"},{"1027":"ЗА"},{"1014":"ЗА"},{"1036":"ЗА"}],"voteTimestamp":"20.10.17 10:25:55"},{"voteName":"пропозиція: включити до порядку денного питання Про надання дозволу на розроблення проекту землеустрою щодо відведення земельної ділянки обслуговування багатоквартирного житлового будинку ","namedVoting":[{"1016":"ЗА"},{"1023":"ЗА"},{"1031":"ЗА"},{"1033":"ЗА"},{"1012":"ЗА"},{"1013":"ЗА"},{"1037":"ЗА"},{"1022":"НЕ ГОЛОСУВАВ"},{"1004":"ЗА"},{"1028":"ЗА"},{"1032":"ЗА"},{"1029":"ЗА"},{"1015":"ЗА"},{"1009":"ЗА"},{"1006":"ЗА"},{"1025":"НЕ ГОЛОСУВАВ"},{"1030":"ЗА"},{"1034":"ЗА"},{"1017":"ЗА"},{"1035":"ЗА"},{"1003":"ЗА"},{"1026":"ЗА"},{"1010":"ЗА"},{"1018":"НЕ ГОЛОСУВАВ"},{"1001":"ЗА"},{"1019":"ЗА"},{"1007":"ЗА"},{"1011":"ЗА"},{"1020":"ЗА"},{"1005":"ЗА"},{"1021":"ЗА"},{"1024":"ЗА"},{"1002":"ЗА"},{"1027":"ЗА"},{"1014":"ЗА"},{"1036":"ЗА"}],"voteTimestamp":"20.10.17 10:26:46"},{"voteName":"пропозиція: включити до порядку денного питання Про скасування п. 3 рішення виконавчого комітету Дрогобицької міської ради від 24 квітня 2014 р. №","namedVoting":[{"1016":"НЕ ГОЛОСУВАВ"},{"1023":"ЗА"},{"1031":"ЗА"},{"1033":"НЕ ГОЛОСУВАВ"},{"1012":"ЗА"},{"1013":"НЕ ГОЛОСУВАВ"},{"1037":"ЗА"},{"1022":"ВІДСУТНІЙ"},{"1004":"НЕ ГОЛОСУВАВ"},{"1028":"НЕ ГОЛОСУВАВ"},{"1032":"НЕ ГОЛОСУВАВ"},{"1029":"НЕ ГОЛОСУВАВ"},{"1015":"ЗА"},{"1009":"НЕ ГОЛОСУВАВ"},{"1006":"ЗА"},{"1025":"ВІДСУТНІЙ"},{"1030":"ЗА"},{"1034":"ЗА"},{"1017":"НЕ ГОЛОСУВАВ"},{"1035":"НЕ ГОЛОСУВАВ"},{"1003":"НЕ ГОЛОСУВАВ"},{"1026":"НЕ ГОЛОСУВАВ"},{"1010":"ЗА"},{"1018":"ВІДСУТНІЙ"},{"1001":"ЗА"},{"1019":"НЕ ГОЛОСУВАВ"},{"1007":"ЗА"},{"1011":"ЗА"},{"1020":"ЗА"},{"1005":"НЕ ГОЛОСУВАВ"},{"1021":"НЕ ГОЛОСУВАВ"},{"1024":"НЕ ГОЛОСУВАВ"},{"1002":"ЗА"},{"1027":"ЗА"},{"1014":"ЗА"},{"1036":"ПРОТИ"}],"voteTimestamp":"20.10.17 10:31:32"},{"voteName":"пропозиція: включити до порядку денного питання Про надання дозволу на розроблення проектів землеустрою щодо відведення земельних ділянок для будівництва та обслуговування житлових будинків, для учасників АТО та учасників бойових дій і членів їх сімей","namedVoting":[{"1016":"ЗА"},{"1023":"ЗА"},{"1031":"ЗА"},{"1033":"ЗА"},{"1012":"ЗА"},{"1013":"ЗА"},{"1037":"ЗА"},{"1022":"ВІДСУТНІЙ"},{"1004":"ЗА"},{"1028":"ЗА"},{"1032":"ЗА"},{"1029":"ЗА"},{"1015":"ЗА"},{"1009":"ЗА"},{"1006":"ЗА"},{"1025":"ВІДСУТНІЙ"},{"1030":"ЗА"},{"1034":"ЗА"},{"1017":"ЗА"},{"1035":"ЗА"},{"1003":"ЗА"},{"1026":"ЗА"},{"1010":"ЗА"},{"1018":"ВІДСУТНІЙ"},{"1001":"ЗА"},{"1019":"ЗА"},{"1007":"ЗА"},{"1011":"ЗА"},{"1020":"ЗА"},{"1005":"ЗА"},{"1021":"ЗА"},{"1024":"ЗА"},{"1002":"ЗА"},{"1027":"ЗА"},{"1014":"ЗА"},{"1036":"ЗА"}],"voteTimestamp":"20.10.17 10:32:29"},{"voteName":"пропозиція: включити до порядку денного питання Про внесення змін до рішення сесії Дрогобицької міської ради №739 від 11.05.2017р «Про передачу в оренду нежитлових приміщень за адресою: м.Дрогобич вул. В.Великого, 26а","namedVoting":[{"1016":"ЗА"},{"1023":"ЗА"},{"1031":"ЗА"},{"1033":"ЗА"},{"1012":"НЕ ГОЛОСУВАВ"},{"1013":"ЗА"},{"1037":"ЗА"},{"1022":"ВІДСУТНІЙ"},{"1004":"ЗА"},{"1028":"ЗА"},{"1032":"ЗА"},{"1029":"ЗА"},{"1015":"ЗА"},{"1009":"ЗА"},{"1006":"НЕ ГОЛОСУВАВ"},{"1025":"ВІДСУТНІЙ"},{"1030":"ЗА"},{"1034":"ЗА"},{"1017":"ЗА"},{"1035":"ЗА"},{"1003":"ЗА"},{"1026":"ЗА"},{"1010":"ЗА"},{"1018":"ВІДСУТНІЙ"},{"1001":"ЗА"},{"1019":"ЗА"},{"1007":"ЗА"},{"1011":"ЗА"},{"1020":"НЕ ГОЛОСУВАВ"},{"1005":"ЗА"},{"1021":"ЗА"},{"1024":"ЗА"},{"1002":"НЕ ГОЛОСУВАВ"},{"1027":"ЗА"},{"1014":"ЗА"},{"1036":"ЗА"}],"voteTimestamp":"20.10.17 10:33:22"},{"voteName":"пропозиція: включити до порядку денного питання Про продовження терміну дії рішення міської ради від 31.01.2014 року № 1241","namedVoting":[{"1016":"ЗА"},{"1023":"ЗА"},{"1031":"ЗА"},{"1033":"ЗА"},{"1012":"НЕ ГОЛОСУВАВ"},{"1013":"ЗА"},{"1037":"ЗА"},{"1022":"ВІДСУТНІЙ"},{"1004":"ЗА"},{"1028":"ЗА"},{"1032":"ЗА"},{"1029":"ЗА"},{"1015":"ЗА"},{"1009":"ЗА"},{"1006":"ЗА"},{"1025":"ВІДСУТНІЙ"},{"1030":"ЗА"},{"1034":"ЗА"},{"1017":"ЗА"},{"1035":"НЕ ГОЛОСУВАВ"},{"1003":"ЗА"},{"1026":"ЗА"},{"1010":"ЗА"},{"1018":"ВІДСУТНІЙ"},{"1001":"ЗА"},{"1019":"ЗА"},{"1007":"ЗА"},{"1011":"ЗА"},{"1020":"ЗА"},{"1005":"ЗА"},{"1021":"ЗА"},{"1024":"ЗА"},{"1002":"ЗА"},{"1027":"ЗА"},{"1014":"ЗА"},{"1036":"ЗА"}],"voteTimestamp":"20.10.17 10:34:41"},{"voteName":"пропозиція: включити до порядку денного питання Про затвердження проекту землеустрою щодо відведення земельної ділянки, площею 0,2050га по вул. Грінченка, включеної в перелік для продажу на земельних торгах у формі аукціону та надання дозволу на виготовлення звіту про експертну грошову оцінку","namedVoting":[{"1016":"ЗА"},{"1023":"ЗА"},{"1031":"ЗА"},{"1033":"ЗА"},{"1012":"НЕ ГОЛОСУВАВ"},{"1013":"ЗА"},{"1037":"ЗА"},{"1022":"ВІДСУТНІЙ"},{"1004":"ЗА"},{"1028":"ЗА"},{"1032":"ЗА"},{"1029":"ЗА"},{"1015":"ЗА"},{"1009":"ЗА"},{"1006":"ЗА"},{"1025":"ВІДСУТНІЙ"},{"1030":"ЗА"},{"1034":"ЗА"},{"1017":"ЗА"},{"1035":"ЗА"},{"1003":"ЗА"},{"1026":"ЗА"},{"1010":"ЗА"},{"1018":"ВІДСУТНІЙ"},{"1001":"ЗА"},{"1019":"ЗА"},{"1007":"ЗА"},{"1011":"ЗА"},{"1020":"ЗА"},{"1005":"ЗА"},{"1021":"ЗА"},{"1024":"ЗА"},{"1002":"НЕ ГОЛОСУВАВ"},{"1027":"ЗА"},{"1014":"ЗА"},{"1036":"ЗА"}],"voteTimestamp":"20.10.17 10:35:38"},{"voteName":"Про затвердження порядку денного ХХVІІІ сесії Дрогобицької міської ради","namedVoting":[{"1016":"ЗА"},{"1023":"ЗА"},{"1031":"ЗА"},{"1033":"ЗА"},{"1012":"ЗА"},{"1013":"ЗА"},{"1037":"ЗА"},{"1022":"ВІДСУТНІЙ"},{"1004":"ЗА"},{"1028":"ЗА"},{"1032":"ЗА"},{"1029":"ЗА"},{"1015":"ЗА"},{"1009":"ЗА"},{"1006":"ЗА"},{"1025":"ВІДСУТНІЙ"},{"1030":"ЗА"},{"1034":"ЗА"},{"1017":"ЗА"},{"1035":"ЗА"},{"1003":"ЗА"},{"1026":"ЗА"},{"1010":"ЗА"},{"1018":"ВІДСУТНІЙ"},{"1001":"ЗА"},{"1019":"ЗА"},{"1007":"ЗА"},{"1011":"ЗА"},{"1020":"ЗА"},{"1005":"ЗА"},{"1021":"ЗА"},{"1024":"ЗА"},{"1002":"ЗА"},{"1027":"ЗА"},{"1014":"ЗА"},{"1036":"ЗА"}],"voteTimestamp":"20.10.17 10:36:16"},{"voteName":"Про внесення змін до міського бюджету м. Дрогобича на 2017 рік","namedVoting":[{"1016":"ЗА"},{"1023":"ЗА"},{"1031":"ЗА"},{"1033":"ЗА"},{"1012":"ЗА"},{"1013":"ЗА"},{"1037":"ЗА"},{"1022":"ВІДСУТНІЙ"},{"1004":"ЗА"},{"1028":"ЗА"},{"1032":"ЗА"},{"1029":"ЗА"},{"1015":"ЗА"},{"1009":"ЗА"},{"1006":"ЗА"},{"1025":"ВІДСУТНІЙ"},{"1030":"ЗА"},{"1034":"ЗА"},{"1017":"ЗА"},{"1035":"ЗА"},{"1003":"ЗА"},{"1026":"ЗА"},{"1010":"ЗА"},{"1018":"ВІДСУТНІЙ"},{"1001":"ЗА"},{"1019":"ЗА"},{"1007":"ЗА"},{"1011":"ЗА"},{"1020":"ЗА"},{"1005":"ЗА"},{"1021":"ЗА"},{"1024":"ЗА"},{"1002":"ВІДСУТНІЙ"},{"1027":"ЗА"},{"1014":"ЗА"},{"1036":"ЗА"}],"voteTimestamp":"20.10.17 11:05:18"},{"voteName":"За поправку до № 2.1. від 20.10.17: Про внесення змін до міського бюджету м. Дрогобича на 2017 рік; доповнення: виділити 489 тис. грн. для придбання обладнання в ЦНАП ","namedVoting":[{"1016":"НЕ ГОЛОСУВАВ"},{"1023":"ЗА"},{"1031":"ЗА"},{"1033":"ЗА"},{"1012":"НЕ ГОЛОСУВАВ"},{"1013":"ЗА"},{"1037":"ЗА"},{"1022":"ВІДСУТНІЙ"},{"1004":"ЗА"},{"1028":"ЗА"},{"1032":"ЗА"},{"1029":"ЗА"},{"1015":"ЗА"},{"1009":"ЗА"},{"1006":"ЗА"},{"1025":"ВІДСУТНІЙ"},{"1030":"ЗА"},{"1034":"ЗА"},{"1017":"ЗА"},{"1035":"ЗА"},{"1003":"ЗА"},{"1026":"ЗА"},{"1010":"ЗА"},{"1018":"ВІДСУТНІЙ"},{"1001":"ЗА"},{"1019":"ЗА"},{"1007":"ЗА"},{"1011":"ЗА"},{"1020":"ЗА"},{"1005":"ЗА"},{"1021":"ЗА"},{"1024":"ЗА"},{"1002":"ВІДСУТНІЙ"},{"1027":"ЗА"},{"1014":"ЗА"},{"1036":"ЗА"}],"voteTimestamp":"20.10.17 11:06:18"},{"voteName":" За поправку до № 2.1. від 20.10.17: Про внесення змін до міського бюджету м. Дрогобича на 2017 рік; доповнення: виділити кошти на проведення ремонтних робіт Палацу мистецтв, поповнення бібліотечного фоенду, на вул.Шевську, відновлення житла для сім\u2019ї учасника АТО","namedVoting":[{"1016":"ЗА"},{"1023":"ЗА"},{"1031":"ЗА"},{"1033":"ЗА"},{"1012":"ЗА"},{"1013":"ЗА"},{"1037":"ЗА"},{"1022":"ВІДСУТНІЙ"},{"1004":"ЗА"},{"1028":"ЗА"},{"1032":"ЗА"},{"1029":"ЗА"},{"1015":"ЗА"},{"1009":"ЗА"},{"1006":"ЗА"},{"1025":"ВІДСУТНІЙ"},{"1030":"НЕ ГОЛОСУВАВ"},{"1034":"ЗА"},{"1017":"ЗА"},{"1035":"ЗА"},{"1003":"ЗА"},{"1026":"ЗА"},{"1010":"ЗА"},{"1018":"ВІДСУТНІЙ"},{"1001":"ЗА"},{"1019":"ЗА"},{"1007":"ЗА"},{"1011":"ЗА"},{"1020":"ЗА"},{"1005":"ЗА"},{"1021":"ЗА"},{"1024":"ЗА"},{"1002":"ВІДСУТНІЙ"},{"1027":"ЗА"},{"1014":"ЗА"},{"1036":"ЗА"}],"voteTimestamp":"20.10.17 11:08:33"},{"voteName":"Про внесення змін до міського бюджету м. Дрогобича на 2017 рік","namedVoting":[{"1016":"ЗА"},{"1023":"ЗА"},{"1031":"ЗА"},{"1033":"ЗА"},{"1012":"ЗА"},{"1013":"ЗА"},{"1037":"ЗА"},{"1022":"ВІДСУТНІЙ"},{"1004":"ЗА"},{"1028":"ЗА"},{"1032":"ЗА"},{"1029":"НЕ ГОЛОСУВАВ"},{"1015":"ЗА"},{"1009":"ЗА"},{"1006":"ЗА"},{"1025":"ВІДСУТНІЙ"},{"1030":"НЕ ГОЛОСУВАВ"},{"1034":"ЗА"},{"1017":"ЗА"},{"1035":"ЗА"},{"1003":"ЗА"},{"1026":"ЗА"},{"1010":"ЗА"},{"1018":"ВІДСУТНІЙ"},{"1001":"ЗА"},{"1019":"ЗА"},{"1007":"ЗА"},{"1011":"ЗА"},{"1020":"ЗА"},{"1005":"ЗА"},{"1021":"ЗА"},{"1024":"ЗА"},{"1002":"ВІДСУТНІЙ"},{"1027":"ЗА"},{"1014":"ЗА"},{"1036":"ЗА"}],"voteTimestamp":"20.10.17 11:09:16"},{"voteName":"Про затвердження експертної оцінки об'єкту комунальної власності Дрогобицької міської ради, який підлягає приватизації шляхом викупу","namedVoting":[{"1016":"НЕ ГОЛОСУВАВ"},{"1023":"ЗА"},{"1031":"ЗА"},{"1033":"ЗА"},{"1012":"ЗА"},{"1013":"ЗА"},{"1037":"ЗА"},{"1022":"ВІДСУТНІЙ"},{"1004":"НЕ ГОЛОСУВАВ"},{"1028":"НЕ ГОЛОСУВАВ"},{"1032":"ЗА"},{"1029":"ЗА"},{"1015":"ЗА"},{"1009":"НЕ ГОЛОСУВАВ"},{"1006":"НЕ ГОЛОСУВАВ"},{"1025":"ВІДСУТНІЙ"},{"1030":"ЗА"},{"1034":"ЗА"},{"1017":"ЗА"},{"1035":"НЕ ГОЛОСУВАВ"},{"1003":"ЗА"},{"1026":"ЗА"},{"1010":"НЕ ГОЛОСУВАВ"},{"1018":"ВІДСУТНІЙ"},{"1001":"УТРИМАВСЯ"},{"1019":"УТРИМАВСЯ"},{"1007":"ЗА"},{"1011":"УТРИМАВСЯ"},{"1020":"ЗА"},{"1005":"ЗА"},{"1021":"УТРИМАВСЯ"},{"1024":"НЕ ГОЛОСУВАВ"},{"1002":"ВІДСУТНІЙ"},{"1027":"ЗА"},{"1014":"ПРОТИ"},{"1036":"ЗА"}],"voteTimestamp":"20.10.17 11:12:03"},{"voteName":"Про включення в перелік об'єктів комунальної власності, що підлягають приватизації шляхом викупу","namedVoting":[{"1016":"ЗА"},{"1023":"ЗА"},{"1031":"ЗА"},{"1033":"ЗА"},{"1012":"НЕ ГОЛОСУВАВ"},{"1013":"ЗА"},{"1037":"ЗА"},{"1022":"ВІДСУТНІЙ"},{"1004":"ЗА"},{"1028":"НЕ ГОЛОСУВАВ"},{"1032":"ЗА"},{"1029":"ЗА"},{"1015":"ЗА"},{"1009":"ЗА"},{"1006":"НЕ ГОЛОСУВАВ"},{"1025":"ВІДСУТНІЙ"},{"1030":"ЗА"},{"1034":"ЗА"},{"1017":"ЗА"},{"1035":"НЕ ГОЛОСУВАВ"},{"1003":"ЗА"},{"1026":"ЗА"},{"1010":"ЗА"},{"1018":"ВІДСУТНІЙ"},{"1001":"ЗА"},{"1019":"ЗА"},{"1007":"ЗА"},{"1011":"ЗА"},{"1020":"ЗА"},{"1005":"ЗА"},{"1021":"ЗА"},{"1024":"ЗА"},{"1002":"ВІДСУТНІЙ"},{"1027":"ЗА"},{"1014":"ЗА"},{"1036":"ЗА"}],"voteTimestamp":"20.10.17 11:12:52"},{"voteName":"Про передачу в оренду нежитлових приміщень та внесення змін в рішення сесії Дрогобицької міської ради № 810 від 30.08.2017р. «Про передачу в оренду нежитлових приміщень»","namedVoting":[{"1016":"ЗА"},{"1023":"ЗА"},{"1031":"ЗА"},{"1033":"ЗА"},{"1012":"НЕ ГОЛОСУВАВ"},{"1013":"ЗА"},{"1037":"ЗА"},{"1022":"ВІДСУТНІЙ"},{"1004":"ЗА"},{"1028":"ЗА"},{"1032":"ЗА"},{"1029":"НЕ ГОЛОСУВАВ"},{"1015":"ЗА"},{"1009":"ЗА"},{"1006":"НЕ ГОЛОСУВАВ"},{"1025":"ВІДСУТНІЙ"},{"1030":"ЗА"},{"1034":"ЗА"},{"1017":"ЗА"},{"1035":"ВІДСУТНІЙ"},{"1003":"ЗА"},{"1026":"ЗА"},{"1010":"ЗА"},{"1018":"ВІДСУТНІЙ"},{"1001":"ЗА"},{"1019":"ЗА"},{"1007":"ЗА"},{"1011":"ЗА"},{"1020":"ЗА"},{"1005":"ЗА"},{"1021":"ЗА"},{"1024":"НЕ ГОЛОСУВАВ"},{"1002":"ВІДСУТНІЙ"},{"1027":"ЗА"},{"1014":"НЕ ГОЛОСУВАВ"},{"1036":"ЗА"}],"voteTimestamp":"20.10.17 11:13:37"},{"voteName":"За поправку до № 3.3. від 20.10.17 : Про передачу в оренду нежитлових приміщень та внесення змін в рішення сесії Дрогобицької міської ради № 810 від 30.08.2017р. «Про передачу в оренду нежитлових приміщень»; прпозиція: зняти з розгляду п. 2, п.п. 2.1 (В.Петречко)","namedVoting":[{"1016":"ЗА"},{"1023":"НЕ ГОЛОСУВАВ"},{"1031":"ЗА"},{"1033":"НЕ ГОЛОСУВАВ"},{"1012":"ЗА"},{"1013":"ЗА"},{"1037":"ЗА"},{"1022":"ВІДСУТНІЙ"},{"1004":"ЗА"},{"1028":"ЗА"},{"1032":"НЕ ГОЛОСУВАВ"},{"1029":"НЕ ГОЛОСУВАВ"},{"1015":"ЗА"},{"1009":"ЗА"},{"1006":"ЗА"},{"1025":"ВІДСУТНІЙ"},{"1030":"НЕ ГОЛОСУВАВ"},{"1034":"ЗА"},{"1017":"ЗА"},{"1035":"ВІДСУТНІЙ"},{"1003":"НЕ ГОЛОСУВАВ"},{"1026":"НЕ ГОЛОСУВАВ"},{"1010":"ЗА"},{"1018":"ВІДСУТНІЙ"},{"1001":"ЗА"},{"1019":"НЕ ГОЛОСУВАВ"},{"1007":"ЗА"},{"1011":"ЗА"},{"1020":"ЗА"},{"1005":"НЕ ГОЛОСУВАВ"},{"1021":"ЗА"},{"1024":"НЕ ГОЛОСУВАВ"},{"1002":"ВІДСУТНІЙ"},{"1027":"НЕ ГОЛОСУВАВ"},{"1014":"ЗА"},{"1036":"УТРИМАВСЯ"}],"voteTimestamp":"20.10.17 11:15:45"},{"voteName":"Про передачу в оренду нежитлових приміщень та внесення змін в рішення сесії Дрогобицької міської ради № 810 від 30.08.2017р. «Про передачу в оренду нежитлових приміщень»","namedVoting":[{"1016":"ЗА"},{"1023":"ЗА"},{"1031":"ЗА"},{"1033":"ЗА"},{"1012":"ЗА"},{"1013":"ЗА"},{"1037":"ЗА"},{"1022":"ВІДСУТНІЙ"},{"1004":"ЗА"},{"1028":"ЗА"},{"1032":"ЗА"},{"1029":"ЗА"},{"1015":"ЗА"},{"1009":"ЗА"},{"1006":"ЗА"},{"1025":"ВІДСУТНІЙ"},{"1030":"ЗА"},{"1034":"ЗА"},{"1017":"ЗА"},{"1035":"ВІДСУТНІЙ"},{"1003":"ЗА"},{"1026":"ЗА"},{"1010":"ЗА"},{"1018":"ВІДСУТНІЙ"},{"1001":"ЗА"},{"1019":"ЗА"},{"1007":"ЗА"},{"1011":"ЗА"},{"1020":"НЕ ГОЛОСУВАВ"},{"1005":"ЗА"},{"1021":"ЗА"},{"1024":"ЗА"},{"1002":"ВІДСУТНІЙ"},{"1027":"ЗА"},{"1014":"ЗА"},{"1036":"ЗА"}],"voteTimestamp":"20.10.17 11:19:45"},{"voteName":"Про надання дозволу на списання основних засобів","namedVoting":[{"1016":"ЗА"},{"1023":"ЗА"},{"1031":"ЗА"},{"1033":"ЗА"},{"1012":"НЕ ГОЛОСУВАВ"},{"1013":"ЗА"},{"1037":"ЗА"},{"1022":"ВІДСУТНІЙ"},{"1004":"ЗА"},{"1028":"ЗА"},{"1032":"ЗА"},{"1029":"ЗА"},{"1015":"ЗА"},{"1009":"ЗА"},{"1006":"ЗА"},{"1025":"ВІДСУТНІЙ"},{"1030":"ЗА"},{"1034":"ЗА"},{"1017":"ЗА"},{"1035":"ВІДСУТНІЙ"},{"1003":"ЗА"},{"1026":"ЗА"},{"1010":"ЗА"},{"1018":"ВІДСУТНІЙ"},{"1001":"ЗА"},{"1019":"ЗА"},{"1007":"ЗА"},{"1011":"ЗА"},{"1020":"ЗА"},{"1005":"ЗА"},{"1021":"НЕ ГОЛОСУВАВ"},{"1024":"ЗА"},{"1002":"ВІДСУТНІЙ"},{"1027":"ЗА"},{"1014":"ЗА"},{"1036":"ЗА"}],"voteTimestamp":"20.10.17 11:20:27"},{"voteName":"Про передачу на баланс матеріальних цінностей","namedVoting":[{"1016":"ЗА"},{"1023":"ЗА"},{"1031":"ЗА"},{"1033":"ЗА"},{"1012":"ЗА"},{"1013":"ЗА"},{"1037":"ЗА"},{"1022":"ВІДСУТНІЙ"},{"1004":"ЗА"},{"1028":"ЗА"},{"1032":"ЗА"},{"1029":"ЗА"},{"1015":"ЗА"},{"1009":"ЗА"},{"1006":"ЗА"},{"1025":"ВІДСУТНІЙ"},{"1030":"ЗА"},{"1034":"ЗА"},{"1017":"ЗА"},{"1035":"ВІДСУТНІЙ"},{"1003":"ЗА"},{"1026":"ЗА"},{"1010":"ЗА"},{"1018":"ВІДСУТНІЙ"},{"1001":"ЗА"},{"1019":"ЗА"},{"1007":"ЗА"},{"1011":"ЗА"},{"1020":"ЗА"},{"1005":"ЗА"},{"1021":"ЗА"},{"1024":"ЗА"},{"1002":"ВІДСУТНІЙ"},{"1027":"ЗА"},{"1014":"ЗА"},{"1036":"ЗА"}],"voteTimestamp":"20.10.17 11:21:01"},{"voteName":"змінити порядок голосування та заслухати питання Про внесення змін до рішення сесії Дрогобицької міської ради №739 від 11.05.2017р; Про передачу в оренду нежитлових приміщень за адресою: м.Дрогобич вул. В.Великого, 26а","namedVoting":[{"1016":"ЗА"},{"1023":"ЗА"},{"1031":"ЗА"},{"1033":"ЗА"},{"1012":"НЕ ГОЛОСУВАВ"},{"1013":"ЗА"},{"1037":"ЗА"},{"1022":"ВІДСУТНІЙ"},{"1004":"ЗА"},{"1028":"ЗА"},{"1032":"ЗА"},{"1029":"ЗА"},{"1015":"ЗА"},{"1009":"ЗА"},{"1006":"НЕ ГОЛОСУВАВ"},{"1025":"ВІДСУТНІЙ"},{"1030":"ЗА"},{"1034":"ЗА"},{"1017":"ЗА"},{"1035":"ВІДСУТНІЙ"},{"1003":"ЗА"},{"1026":"ЗА"},{"1010":"ЗА"},{"1018":"ВІДСУТНІЙ"},{"1001":"ЗА"},{"1019":"ЗА"},{"1007":"ЗА"},{"1011":"ЗА"},{"1020":"ЗА"},{"1005":"ЗА"},{"1021":"ЗА"},{"1024":"ЗА"},{"1002":"ВІДСУТНІЙ"},{"1027":"ЗА"},{"1014":"ЗА"},{"1036":"ЗА"}],"voteTimestamp":"20.10.17 11:21:52"},{"voteName":"Про внесення змін до рішення сесії Дрогобицької міської ради №739 від 11.05.2017р «Про передачу в оренду нежитлових приміщень за адресою: м.Дрогобич вул. В.Великого, 26а»","namedVoting":[{"1016":"ЗА"},{"1023":"ЗА"},{"1031":"ЗА"},{"1033":"ЗА"},{"1012":"НЕ ГОЛОСУВАВ"},{"1013":"ЗА"},{"1037":"ЗА"},{"1022":"ВІДСУТНІЙ"},{"1004":"ЗА"},{"1028":"ЗА"},{"1032":"ЗА"},{"1029":"НЕ ГОЛОСУВАВ"},{"1015":"ЗА"},{"1009":"ЗА"},{"1006":"ЗА"},{"1025":"ВІДСУТНІЙ"},{"1030":"ЗА"},{"1034":"ЗА"},{"1017":"ЗА"},{"1035":"ВІДСУТНІЙ"},{"1003":"ЗА"},{"1026":"ЗА"},{"1010":"НЕ ГОЛОСУВАВ"},{"1018":"ВІДСУТНІЙ"},{"1001":"ЗА"},{"1019":"ЗА"},{"1007":"ЗА"},{"1011":"ЗА"},{"1020":"ЗА"},{"1005":"ЗА"},{"1021":"ЗА"},{"1024":"ЗА"},{"1002":"ВІДСУТНІЙ"},{"1027":"ЗА"},{"1014":"ЗА"},{"1036":"ЗА"}],"voteTimestamp":"20.10.17 11:22:50"},{"voteName":"Про внесення змін до рішення сесії Дрогобицької міської ради №739 від 11.05.2017р «Про передачу в оренду нежитлових приміщень за адресою: м.Дрогобич вул. В.Великого, 26а»","namedVoting":[{"1016":"ЗА"},{"1023":"ЗА"},{"1031":"ЗА"},{"1033":"ЗА"},{"1012":"НЕ ГОЛОСУВАВ"},{"1013":"ЗА"},{"1037":"ЗА"},{"1022":"ВІДСУТНІЙ"},{"1004":"ЗА"},{"1028":"НЕ ГОЛОСУВАВ"},{"1032":"ЗА"},{"1029":"ЗА"},{"1015":"ЗА"},{"1009":"ЗА"},{"1006":"НЕ ГОЛОСУВАВ"},{"1025":"ВІДСУТНІЙ"},{"1030":"ЗА"},{"1034":"ЗА"},{"1017":"НЕ ГОЛОСУВАВ"},{"1035":"ВІДСУТНІЙ"},{"1003":"ЗА"},{"1026":"ЗА"},{"1010":"ЗА"},{"1018":"ВІДСУТНІЙ"},{"1001":"ЗА"},{"1019":"ЗА"},{"1007":"ЗА"},{"1011":"ЗА"},{"1020":"ЗА"},{"1005":"ЗА"},{"1021":"ЗА"},{"1024":"ЗА"},{"1002":"ВІДСУТНІЙ"},{"1027":"ЗА"},{"1014":"УТРИМАВСЯ"},{"1036":"ЗА"}],"voteTimestamp":"20.10.17 11:29:17"},{"voteName":"змінити порядок голосування та розглянути питання Про надання дозволу на розроблення проектів землеустрою щодо відведення земельних ділянок для будівництва та обслуговування житлових будинків, для учасників АТО та учасників бойових дій і членів","namedVoting":[{"1016":"ЗА"},{"1023":"ЗА"},{"1031":"ЗА"},{"1033":"ЗА"},{"1012":"ЗА"},{"1013":"ЗА"},{"1037":"НЕ ГОЛОСУВАВ"},{"1022":"ВІДСУТНІЙ"},{"1004":"ЗА"},{"1028":"НЕ ГОЛОСУВАВ"},{"1032":"ЗА"},{"1029":"ЗА"},{"1015":"ЗА"},{"1009":"ЗА"},{"1006":"ЗА"},{"1025":"ВІДСУТНІЙ"},{"1030":"ЗА"},{"1034":"ЗА"},{"1017":"ЗА"},{"1035":"ВІДСУТНІЙ"},{"1003":"ЗА"},{"1026":"ЗА"},{"1010":"ЗА"},{"1018":"ВІДСУТНІЙ"},{"1001":"ЗА"},{"1019":"ЗА"},{"1007":"ЗА"},{"1011":"ЗА"},{"1020":"ЗА"},{"1005":"ЗА"},{"1021":"ЗА"},{"1024":"ЗА"},{"1002":"ВІДСУТНІЙ"},{"1027":"ЗА"},{"1014":"ЗА"},{"1036":"ЗА"}],"voteTimestamp":"20.10.17 11:30:18"},{"voteName":"Про надання дозволу на розроблення проектів землеустрою щодо відведення земельних ділянок для будівництва та обслуговування житлових будинків, для учасників АТО та учасників бойових дій і членів їх сімей","namedVoting":[{"1016":"ЗА"},{"1023":"ЗА"},{"1031":"ЗА"},{"1033":"ЗА"},{"1012":"ЗА"},{"1013":"ЗА"},{"1037":"ЗА"},{"1022":"ВІДСУТНІЙ"},{"1004":"ЗА"},{"1028":"НЕ ГОЛОСУВАВ"},{"1032":"ЗА"},{"1029":"ЗА"},{"1015":"ЗА"},{"1009":"ЗА"},{"1006":"ЗА"},{"1025":"ВІДСУТНІЙ"},{"1030":"ЗА"},{"1034":"ЗА"},{"1017":"ЗА"},{"1035":"ВІДСУТНІЙ"},{"1003":"ЗА"},{"1026":"ЗА"},{"1010":"ЗА"},{"1018":"ВІДСУТНІЙ"},{"1001":"ЗА"},{"1019":"ЗА"},{"1007":"ЗА"},{"1011":"ЗА"},{"1020":"ЗА"},{"1005":"ЗА"},{"1021":"ЗА"},{"1024":"ЗА"},{"1002":"ВІДСУТНІЙ"},{"1027":"ЗА"},{"1014":"ЗА"},{"1036":"ЗА"}],"voteTimestamp":"20.10.17 11:31:17"},{"voteName":"Про відмову у наданні дозволів на виготовлення проектів землеустрою щодо відведення земельних ділянок, у наданні згоди на виготовлення технічної документації земельної ділянки, у наданні в оренду земельної ділянки, у включенні в перелік для продажу земельних ділянок несільськогосподарського призначення\u201D ","namedVoting":[{"1016":"ЗА"},{"1023":"ЗА"},{"1031":"ЗА"},{"1033":"ЗА"},{"1012":"НЕ ГОЛОСУВАВ"},{"1013":"ЗА"},{"1037":"НЕ ГОЛОСУВАВ"},{"1022":"ВІДСУТНІЙ"},{"1004":"НЕ ГОЛОСУВАВ"},{"1028":"ЗА"},{"1032":"ЗА"},{"1029":"ЗА"},{"1015":"ЗА"},{"1009":"ЗА"},{"1006":"НЕ ГОЛОСУВАВ"},{"1025":"ВІДСУТНІЙ"},{"1030":"ЗА"},{"1034":"ЗА"},{"1017":"ЗА"},{"1035":"ВІДСУТНІЙ"},{"1003":"ЗА"},{"1026":"ЗА"},{"1010":"НЕ ГОЛОСУВАВ"},{"1018":"ВІДСУТНІЙ"},{"1001":"ЗА"},{"1019":"ЗА"},{"1007":"ЗА"},{"1011":"НЕ ГОЛОСУВАВ"},{"1020":"ЗА"},{"1005":"ЗА"},{"1021":"ЗА"},{"1024":"ЗА"},{"1002":"ВІДСУТНІЙ"},{"1027":"ЗА"},{"1014":"НЕ ГОЛОСУВАВ"},{"1036":"ЗА"}],"voteTimestamp":"20.10.17 11:33:09"},{"voteName":"Про надання дозволу на розроблення проектів землеустрою щодо відведення земельних ділянок для будівництва та обслуговування житлових будинків (присадибна ділянка)","namedVoting":[{"1016":"ЗА"},{"1023":"ЗА"},{"1031":"ЗА"},{"1033":"ЗА"},{"1012":"НЕ ГОЛОСУВАВ"},{"1013":"НЕ ГОЛОСУВАВ"},{"1037":"ЗА"},{"1022":"ВІДСУТНІЙ"},{"1004":"ЗА"},{"1028":"ЗА"},{"1032":"ЗА"},{"1029":"ЗА"},{"1015":"ЗА"},{"1009":"ЗА"},{"1006":"НЕ ГОЛОСУВАВ"},{"1025":"ВІДСУТНІЙ"},{"1030":"ЗА"},{"1034":"ЗА"},{"1017":"ЗА"},{"1035":"ВІДСУТНІЙ"},{"1003":"ЗА"},{"1026":"ЗА"},{"1010":"ЗА"},{"1018":"ВІДСУТНІЙ"},{"1001":"ЗА"},{"1019":"ЗА"},{"1007":"ЗА"},{"1011":"ЗА"},{"1020":"ЗА"},{"1005":"ЗА"},{"1021":"НЕ ГОЛОСУВАВ"},{"1024":"ЗА"},{"1002":"ВІДСУТНІЙ"},{"1027":"ЗА"},{"1014":"ЗА"},{"1036":"ЗА"}],"voteTimestamp":"20.10.17 11:33:56"},{"voteName":"За поправку до № 4.2. від 20.10.17 Про надання дозволу на розроблення проектів землеустрою щодо відведення земельних ділянок для будівництва та обслуговування житлових будинків (присадибна ділянка); пропозиція: у п.п. 1.1. (ОСББ Зелена брама\u201D) зміни в площі № 1 від 20.10.17","namedVoting":[{"1016":"ЗА"},{"1023":"ЗА"},{"1031":"ЗА"},{"1033":"ЗА"},{"1012":"НЕ ГОЛОСУВАВ"},{"1013":"ЗА"},{"1037":"ЗА"},{"1022":"ВІДСУТНІЙ"},{"1004":"НЕ ГОЛОСУВАВ"},{"1028":"ЗА"},{"1032":"ЗА"},{"1029":"ЗА"},{"1015":"ЗА"},{"1009":"ЗА"},{"1006":"НЕ ГОЛОСУВАВ"},{"1025":"ВІДСУТНІЙ"},{"1030":"ЗА"},{"1034":"ЗА"},{"1017":"ЗА"},{"1035":"ВІДСУТНІЙ"},{"1003":"ЗА"},{"1026":"ЗА"},{"1010":"НЕ ГОЛОСУВАВ"},{"1018":"ВІДСУТНІЙ"},{"1001":"ЗА"},{"1019":"ЗА"},{"1007":"ЗА"},{"1011":"ЗА"},{"1020":"ЗА"},{"1005":"ЗА"},{"1021":"НЕ ГОЛОСУВАВ"},{"1024":"ЗА"},{"1002":"НЕ ГОЛОСУВАВ"},{"1027":"ЗА"},{"1014":"НЕ ГОЛОСУВАВ"},{"1036":"ЗА"}],"voteTimestamp":"20.10.17 11:35:32"},{"voteName":"За поправку до № 4.2. від 20.10.17 Про надання дозволу на розроблення проектів землеустрою щодо відведення земельних ділянок для будівництва та обслуговування житлових будинків (присадибна ділянка); прпозиція: у п.п. 1.4 (ОСББ Тріо 16\u201D) зміни в площі","namedVoting":[{"1016":"ЗА"},{"1023":"ЗА"},{"1031":"ЗА"},{"1033":"ЗА"},{"1012":"НЕ ГОЛОСУВАВ"},{"1013":"ЗА"},{"1037":"ЗА"},{"1022":"ВІДСУТНІЙ"},{"1004":"ЗА"},{"1028":"ЗА"},{"1032":"ЗА"},{"1029":"ЗА"},{"1015":"ЗА"},{"1009":"ЗА"},{"1006":"НЕ ГОЛОСУВАВ"},{"1025":"ВІДСУТНІЙ"},{"1030":"ЗА"},{"1034":"ЗА"},{"1017":"ЗА"},{"1035":"ВІДСУТНІЙ"},{"1003":"ЗА"},{"1026":"ЗА"},{"1010":"ЗА"},{"1018":"ВІДСУТНІЙ"},{"1001":"ЗА"},{"1019":"ЗА"},{"1007":"ЗА"},{"1011":"НЕ ГОЛОСУВАВ"},{"1020":"ЗА"},{"1005":"ЗА"},{"1021":"НЕ ГОЛОСУВАВ"},{"1024":"ЗА"},{"1002":"НЕ ГОЛОСУВАВ"},{"1027":"ЗА"},{"1014":"ЗА"},{"1036":"ЗА"}],"voteTimestamp":"20.10.17 11:36:48"},{"voteName":"Про надання дозволу на розроблення проектів землеустрою щодо відведення земельних ділянок для будівництва та обслуговування житлових будинків (присадибна ділянка)","namedVoting":[{"1016":"ЗА"},{"1023":"ЗА"},{"1031":"ЗА"},{"1033":"ЗА"},{"1012":"НЕ ГОЛОСУВАВ"},{"1013":"ЗА"},{"1037":"ЗА"},{"1022":"ВІДСУТНІЙ"},{"1004":"ЗА"},{"1028":"ЗА"},{"1032":"ЗА"},{"1029":"ЗА"},{"1015":"ЗА"},{"1009":"ЗА"},{"1006":"НЕ ГОЛОСУВАВ"},{"1025":"ВІДСУТНІЙ"},{"1030":"ЗА"},{"1034":"ЗА"},{"1017":"ЗА"},{"1035":"ВІДСУТНІЙ"},{"1003":"ЗА"},{"1026":"ЗА"},{"1010":"ЗА"},{"1018":"ВІДСУТНІЙ"},{"1001":"ЗА"},{"1019":"ЗА"},{"1007":"ЗА"},{"1011":"ЗА"},{"1020":"ЗА"},{"1005":"ЗА"},{"1021":"НЕ ГОЛОСУВАВ"},{"1024":"ЗА"},{"1002":"ЗА"},{"1027":"ЗА"},{"1014":"ЗА"},{"1036":"ЗА"}],"voteTimestamp":"20.10.17 11:37:24"},{"voteName":"Про надання згоди на укладення договорів про встановлення особистого строкового сервітуту для розміщення МАФ","namedVoting":[{"1016":"ЗА"},{"1023":"ЗА"},{"1031":"НЕ ГОЛОСУВАВ"},{"1033":"ЗА"},{"1012":"НЕ ГОЛОСУВАВ"},{"1013":"ЗА"},{"1037":"НЕ ГОЛОСУВАВ"},{"1022":"ВІДСУТНІЙ"},{"1004":"ЗА"},{"1028":"НЕ ГОЛОСУВАВ"},{"1032":"ЗА"},{"1029":"ЗА"},{"1015":"ЗА"},{"1009":"ЗА"},{"1006":"НЕ ГОЛОСУВАВ"},{"1025":"ВІДСУТНІЙ"},{"1030":"ЗА"},{"1034":"НЕ ГОЛОСУВАВ"},{"1017":"ЗА"},{"1035":"ВІДСУТНІЙ"},{"1003":"ЗА"},{"1026":"ЗА"},{"1010":"НЕ ГОЛОСУВАВ"},{"1018":"ВІДСУТНІЙ"},{"1001":"ЗА"},{"1019":"ЗА"},{"1007":"УТРИМАВСЯ"},{"1011":"НЕ ГОЛОСУВАВ"},{"1020":"ЗА"},{"1005":"ЗА"},{"1021":"ЗА"},{"1024":"ЗА"},{"1002":"НЕ ГОЛОСУВАВ"},{"1027":"НЕ ГОЛОСУВАВ"},{"1014":"НЕ ГОЛОСУВАВ"},{"1036":"ЗА"}],"voteTimestamp":"20.10.17 11:38:14"},{"voteName":"Про надання згоди на укладення договорів про встановлення особистого строкового сервітуту для розміщення МАФ","namedVoting":[{"1016":"НЕ ГОЛОСУВАВ"},{"1023":"ЗА"},{"1031":"НЕ ГОЛОСУВАВ"},{"1033":"ЗА"},{"1012":"ПРОТИ"},{"1013":"ЗА"},{"1037":"НЕ ГОЛОСУВАВ"},{"1022":"ВІДСУТНІЙ"},{"1004":"НЕ ГОЛОСУВАВ"},{"1028":"НЕ ГОЛОСУВАВ"},{"1032":"ЗА"},{"1029":"ЗА"},{"1015":"УТРИМАВСЯ"},{"1009":"ЗА"},{"1006":"НЕ ГОЛОСУВАВ"},{"1025":"ВІДСУТНІЙ"},{"1030":"ЗА"},{"1034":"НЕ ГОЛОСУВАВ"},{"1017":"НЕ ГОЛОСУВАВ"},{"1035":"ВІДСУТНІЙ"},{"1003":"ЗА"},{"1026":"ЗА"},{"1010":"НЕ ГОЛОСУВАВ"},{"1018":"ВІДСУТНІЙ"},{"1001":"ЗА"},{"1019":"ЗА"},{"1007":"НЕ ГОЛОСУВАВ"},{"1011":"НЕ ГОЛОСУВАВ"},{"1020":"НЕ ГОЛОСУВАВ"},{"1005":"ЗА"},{"1021":"УТРИМАВСЯ"},{"1024":"ЗА"},{"1002":"НЕ ГОЛОСУВАВ"},{"1027":"НЕ ГОЛОСУВАВ"},{"1014":"ПРОТИ"},{"1036":"НЕ ГОЛОСУВАВ"}],"voteTimestamp":"20.10.17 11:40:17"},{"voteName":"Про включення в перелік земельних ділянок несільськогосподарського призначення, які підлягають продажу у власність","namedVoting":[{"1016":"НЕ ГОЛОСУВАВ"},{"1023":"ЗА"},{"1031":"ЗА"},{"1033":"ЗА"},{"1012":"НЕ ГОЛОСУВАВ"},{"1013":"ЗА"},{"1037":"ЗА"},{"1022":"ВІДСУТНІЙ"},{"1004":"ЗА"},{"1028":"НЕ ГОЛОСУВАВ"},{"1032":"ЗА"},{"1029":"ЗА"},{"1015":"ЗА"},{"1009":"ЗА"},{"1006":"НЕ ГОЛОСУВАВ"},{"1025":"ВІДСУТНІЙ"},{"1030":"ЗА"},{"1034":"ЗА"},{"1017":"НЕ ГОЛОСУВАВ"},{"1035":"ВІДСУТНІЙ"},{"1003":"ЗА"},{"1026":"ЗА"},{"1010":"ЗА"},{"1018":"ВІДСУТНІЙ"},{"1001":"ЗА"},{"1019":"ЗА"},{"1007":"ЗА"},{"1011":"ЗА"},{"1020":"ЗА"},{"1005":"ЗА"},{"1021":"ЗА"},{"1024":"ЗА"},{"1002":"НЕ ГОЛОСУВАВ"},{"1027":"НЕ ГОЛОСУВАВ"},{"1014":"НЕ ГОЛОСУВАВ"},{"1036":"ЗА"}],"voteTimestamp":"20.10.17 11:40:55"},{"voteName":"Про надання дозволу на розроблення проектів землеустрою щодо відведення земельних ділянок для ведення садівництва","namedVoting":[{"1016":"ЗА"},{"1023":"ЗА"},{"1031":"ЗА"},{"1033":"ЗА"},{"1012":"НЕ ГОЛОСУВАВ"},{"1013":"ЗА"},{"1037":"ЗА"},{"1022":"ВІДСУТНІЙ"},{"1004":"ЗА"},{"1028":"НЕ ГОЛОСУВАВ"},{"1032":"ЗА"},{"1029":"ЗА"},{"1015":"ЗА"},{"1009":"ЗА"},{"1006":"НЕ ГОЛОСУВАВ"},{"1025":"ВІДСУТНІЙ"},{"1030":"ЗА"},{"1034":"ЗА"},{"1017":"ЗА"},{"1035":"ВІДСУТНІЙ"},{"1003":"ЗА"},{"1026":"ЗА"},{"1010":"НЕ ГОЛОСУВАВ"},{"1018":"ВІДСУТНІЙ"},{"1001":"ЗА"},{"1019":"ЗА"},{"1007":"ЗА"},{"1011":"НЕ ГОЛОСУВАВ"},{"1020":"ЗА"},{"1005":"ЗА"},{"1021":"ЗА"},{"1024":"ЗА"},{"1002":"ЗА"},{"1027":"НЕ ГОЛОСУВАВ"},{"1014":"ЗА"},{"1036":"ЗА"}],"voteTimestamp":"20.10.17 11:41:37"},{"voteName":"За поправку до № 4.5. від 20.10.17 Про надання дозволу на розроблення проектів землеустрою щодо відведення земельних ділянок для","namedVoting":[{"1016":"НЕ ГОЛОСУВАВ"},{"1023":"НЕ ГОЛОСУВАВ"},{"1031":"НЕ ГОЛОСУВАВ"},{"1033":"НЕ ГОЛОСУВАВ"},{"1012":"ЗА"},{"1013":"НЕ ГОЛОСУВАВ"},{"1037":"НЕ ГОЛОСУВАВ"},{"1022":"НЕ ГОЛОСУВАВ"},{"1004":"НЕ ГОЛОСУВАВ"},{"1028":"НЕ ГОЛОСУВАВ"},{"1032":"НЕ ГОЛОСУВАВ"},{"1029":"НЕ ГОЛОСУВАВ"},{"1015":"ЗА"},{"1009":"НЕ ГОЛОСУВАВ"},{"1006":"ЗА"},{"1025":"ВІДСУТНІЙ"},{"1030":"НЕ ГОЛОСУВАВ"},{"1034":"НЕ ГОЛОСУВАВ"},{"1017":"НЕ ГОЛОСУВАВ"},{"1035":"ВІДСУТНІЙ"},{"1003":"НЕ ГОЛОСУВАВ"},{"1026":"НЕ ГОЛОСУВАВ"},{"1010":"НЕ ГОЛОСУВАВ"},{"1018":"ВІДСУТНІЙ"},{"1001":"НЕ ГОЛОСУВАВ"},{"1019":"НЕ ГОЛОСУВАВ"},{"1007":"НЕ ГОЛОСУВАВ"},{"1011":"НЕ ГОЛОСУВАВ"},{"1020":"НЕ ГОЛОСУВАВ"},{"1005":"НЕ ГОЛОСУВАВ"},{"1021":"ЗА"},{"1024":"НЕ ГОЛОСУВАВ"},{"1002":"ЗА"},{"1027":"НЕ ГОЛОСУВАВ"},{"1014":"НЕ ГОЛОСУВАВ"},{"1036":"НЕ ГОЛОСУВАВ"}],"voteTimestamp":"20.10.17 11:47:07"},{"voteName":" За поправку до № 4.5. від 20.10.17 Про надання дозволу на розроблення проектів землеустрою щодо відведення земельних ділянок для","namedVoting":[{"1016":"НЕ ГОЛОСУВАВ"},{"1023":"ЗА"},{"1031":"ЗА"},{"1033":"ЗА"},{"1012":"НЕ ГОЛОСУВАВ"},{"1013":"ЗА"},{"1037":"ЗА"},{"1022":"НЕ ГОЛОСУВАВ"},{"1004":"ЗА"},{"1028":"НЕ ГОЛОСУВАВ"},{"1032":"ЗА"},{"1029":"ЗА"},{"1015":"ЗА"},{"1009":"ЗА"},{"1006":"НЕ ГОЛОСУВАВ"},{"1025":"ВІДСУТНІЙ"},{"1030":"НЕ ГОЛОСУВАВ"},{"1034":"ЗА"},{"1017":"ЗА"},{"1035":"ВІДСУТНІЙ"},{"1003":"ЗА"},{"1026":"ЗА"},{"1010":"НЕ ГОЛОСУВАВ"},{"1018":"ВІДСУТНІЙ"},{"1001":"ЗА"},{"1019":"ЗА"},{"1007":"ЗА"},{"1011":"НЕ ГОЛОСУВАВ"},{"1020":"НЕ ГОЛОСУВАВ"},{"1005":"ЗА"},{"1021":"ЗА"},{"1024":"ЗА"},{"1002":"ЗА"},{"1027":"ЗА"},{"1014":"ЗА"},{"1036":"ЗА"}],"voteTimestamp":"20.10.17 11:48:44"},{"voteName":"За поправку до № 4.5. від 20.10.17 Про надання дозволу на розроблення проектів землеустрою щодо відведення земельних ділянок для","namedVoting":[{"1016":"НЕ ГОЛОСУВАВ"},{"1023":"ЗА"},{"1031":"ЗА"},{"1033":"ЗА"},{"1012":"НЕ ГОЛОСУВАВ"},{"1013":"НЕ ГОЛОСУВАВ"},{"1037":"НЕ ГОЛОСУВАВ"},{"1022":"НЕ ГОЛОСУВАВ"},{"1004":"НЕ ГОЛОСУВАВ"},{"1028":"НЕ ГОЛОСУВАВ"},{"1032":"ЗА"},{"1029":"НЕ ГОЛОСУВАВ"},{"1015":"НЕ ГОЛОСУВАВ"},{"1009":"НЕ ГОЛОСУВАВ"},{"1006":"НЕ ГОЛОСУВАВ"},{"1025":"ВІДСУТНІЙ"},{"1030":"НЕ ГОЛОСУВАВ"},{"1034":"НЕ ГОЛОСУВАВ"},{"1017":"НЕ ГОЛОСУВАВ"},{"1035":"ВІДСУТНІЙ"},{"1003":"ЗА"},{"1026":"ЗА"},{"1010":"НЕ ГОЛОСУВАВ"},{"1018":"ВІДСУТНІЙ"},{"1001":"ЗА"},{"1019":"НЕ ГОЛОСУВАВ"},{"1007":"ЗА"},{"1011":"НЕ ГОЛОСУВАВ"},{"1020":"НЕ ГОЛОСУВАВ"},{"1005":"ЗА"},{"1021":"УТРИМАВСЯ"},{"1024":"ЗА"},{"1002":"НЕ ГОЛОСУВАВ"},{"1027":"ЗА"},{"1014":"НЕ ГОЛОСУВАВ"},{"1036":"НЕ ГОЛОСУВАВ"}],"voteTimestamp":"20.10.17 11:50:29"},{"voteName":"пропозиція: повернутися до голосування пропозиції  - доповнити рішення п.п. 1.12 (І.Сторонський) ","namedVoting":[{"1016":"ЗА"},{"1023":"ЗА"},{"1031":"ЗА"},{"1033":"ЗА"},{"1012":"НЕ ГОЛОСУВАВ"},{"1013":"ЗА"},{"1037":"НЕ ГОЛОСУВАВ"},{"1022":"НЕ ГОЛОСУВАВ"},{"1004":"ЗА"},{"1028":"ЗА"},{"1032":"ЗА"},{"1029":"ЗА"},{"1015":"НЕ ГОЛОСУВАВ"},{"1009":"ЗА"},{"1006":"НЕ ГОЛОСУВАВ"},{"1025":"ВІДСУТНІЙ"},{"1030":"НЕ ГОЛОСУВАВ"},{"1034":"ЗА"},{"1017":"ЗА"},{"1035":"ВІДСУТНІЙ"},{"1003":"ЗА"},{"1026":"ЗА"},{"1010":"НЕ ГОЛОСУВАВ"},{"1018":"ВІДСУТНІЙ"},{"1001":"ЗА"},{"1019":"ЗА"},{"1007":"ЗА"},{"1011":"НЕ ГОЛОСУВАВ"},{"1020":"НЕ ГОЛОСУВАВ"},{"1005":"ЗА"},{"1021":"УТРИМАВСЯ"},{"1024":"НЕ ГОЛОСУВАВ"},{"1002":"ЗА"},{"1027":"ЗА"},{"1014":"ЗА"},{"1036":"ЗА"}],"voteTimestamp":"20.10.17 11:51:57"},{"voteName":" За поправку до № 4.5. від 20.10.17 Про надання дозволу на розроблення проектів землеустрою щодо відведення земельних ділянок для","namedVoting":[{"1016":"НЕ ГОЛОСУВАВ"},{"1023":"ЗА"},{"1031":"ЗА"},{"1033":"ЗА"},{"1012":"НЕ ГОЛОСУВАВ"},{"1013":"ЗА"},{"1037":"НЕ ГОЛОСУВАВ"},{"1022":"ЗА"},{"1004":"ЗА"},{"1028":"НЕ ГОЛОСУВАВ"},{"1032":"ЗА"},{"1029":"ЗА"},{"1015":"ЗА"},{"1009":"ЗА"},{"1006":"НЕ ГОЛОСУВАВ"},{"1025":"ВІДСУТНІЙ"},{"1030":"НЕ ГОЛОСУВАВ"},{"1034":"ЗА"},{"1017":"ЗА"},{"1035":"ВІДСУТНІЙ"},{"1003":"ЗА"},{"1026":"ЗА"},{"1010":"НЕ ГОЛОСУВАВ"},{"1018":"ВІДСУТНІЙ"},{"1001":"ЗА"},{"1019":"ЗА"},{"1007":"ЗА"},{"1011":"НЕ ГОЛОСУВАВ"},{"1020":"НЕ ГОЛОСУВАВ"},{"1005":"ЗА"},{"1021":"ЗА"},{"1024":"ЗА"},{"1002":"НЕ ГОЛОСУВАВ"},{"1027":"ЗА"},{"1014":"НЕ ГОЛОСУВАВ"},{"1036":"НЕ ГОЛОСУВАВ"}],"voteTimestamp":"20.10.17 11:52:41"},{"voteName":"Про надання дозволу на розроблення проектів землеустрою щодо відведення земельних ділянок для ведення садівництва","namedVoting":[{"1016":"НЕ ГОЛОСУВАВ"},{"1023":"ЗА"},{"1031":"ЗА"},{"1033":"ЗА"},{"1012":"НЕ ГОЛОСУВАВ"},{"1013":"ЗА"},{"1037":"ЗА"},{"1022":"ЗА"},{"1004":"ЗА"},{"1028":"НЕ ГОЛОСУВАВ"},{"1032":"ЗА"},{"1029":"ЗА"},{"1015":"ЗА"},{"1009":"ЗА"},{"1006":"НЕ ГОЛОСУВАВ"},{"1025":"ВІДСУТНІЙ"},{"1030":"НЕ ГОЛОСУВАВ"},{"1034":"ЗА"},{"1017":"ЗА"},{"1035":"ВІДСУТНІЙ"},{"1003":"ЗА"},{"1026":"ЗА"},{"1010":"НЕ ГОЛОСУВАВ"},{"1018":"ВІДСУТНІЙ"},{"1001":"ЗА"},{"1019":"ЗА"},{"1007":"ЗА"},{"1011":"НЕ ГОЛОСУВАВ"},{"1020":"НЕ ГОЛОСУВАВ"},{"1005":"ЗА"},{"1021":"ЗА"},{"1024":"ЗА"},{"1002":"НЕ ГОЛОСУВАВ"},{"1027":"НЕ ГОЛОСУВАВ"},{"1014":"ЗА"},{"1036":"ЗА"}],"voteTimestamp":"20.10.17 11:53:15"},{"voteName":"Про внесення змін до рішень міської ради","namedVoting":[{"1016":"ЗА"},{"1023":"ЗА"},{"1031":"ЗА"},{"1033":"ЗА"},{"1012":"НЕ ГОЛОСУВАВ"},{"1013":"ЗА"},{"1037":"ЗА"},{"1022":"НЕ ГОЛОСУВАВ"},{"1004":"ЗА"},{"1028":"НЕ ГОЛОСУВАВ"},{"1032":"ЗА"},{"1029":"НЕ ГОЛОСУВАВ"},{"1015":"ЗА"},{"1009":"ЗА"},{"1006":"ЗА"},{"1025":"ВІДСУТНІЙ"},{"1030":"ЗА"},{"1034":"ЗА"},{"1017":"ЗА"},{"1035":"ВІДСУТНІЙ"},{"1003":"ЗА"},{"1026":"ЗА"},{"1010":"ЗА"},{"1018":"ВІДСУТНІЙ"},{"1001":"ЗА"},{"1019":"ЗА"},{"1007":"ЗА"},{"1011":"ЗА"},{"1020":"ЗА"},{"1005":"ЗА"},{"1021":"НЕ ГОЛОСУВАВ"},{"1024":"ЗА"},{"1002":"ЗА"},{"1027":"ЗА"},{"1014":"ЗА"},{"1036":"ЗА"}],"voteTimestamp":"20.10.17 11:54:07"},{"voteName":"Про надання дозволу на розроблення технічної документації із землеустрою щодо встановлення меж земельної ділянки в натурі (на місцевості)","namedVoting":[{"1016":"ЗА"},{"1023":"ЗА"},{"1031":"ЗА"},{"1033":"ЗА"},{"1012":"НЕ ГОЛОСУВАВ"},{"1013":"ЗА"},{"1037":"ЗА"},{"1022":"ЗА"},{"1004":"ЗА"},{"1028":"НЕ ГОЛОСУВАВ"},{"1032":"ЗА"},{"1029":"ЗА"},{"1015":"ЗА"},{"1009":"ЗА"},{"1006":"ЗА"},{"1025":"ВІДСУТНІЙ"},{"1030":"ЗА"},{"1034":"ЗА"},{"1017":"НЕ ГОЛОСУВАВ"},{"1035":"ВІДСУТНІЙ"},{"1003":"ЗА"},{"1026":"ЗА"},{"1010":"НЕ ГОЛОСУВАВ"},{"1018":"ВІДСУТНІЙ"},{"1001":"ЗА"},{"1019":"ЗА"},{"1007":"ЗА"},{"1011":"НЕ ГОЛОСУВАВ"},{"1020":"ЗА"},{"1005":"ЗА"},{"1021":"ЗА"},{"1024":"ЗА"},{"1002":"ЗА"},{"1027":"ЗА"},{"1014":"ЗА"},{"1036":"ЗА"}],"voteTimestamp":"20.10.17 11:54:47"},{"voteName":"Про припинення договорів про встановлення особистого строкового сервітуту для розміщення МАФ","namedVoting":[{"1016":"ЗА"},{"1023":"ЗА"},{"1031":"ЗА"},{"1033":"ЗА"},{"1012":"ЗА"},{"1013":"ЗА"},{"1037":"ЗА"},{"1022":"НЕ ГОЛОСУВАВ"},{"1004":"ЗА"},{"1028":"ЗА"},{"1032":"ЗА"},{"1029":"ЗА"},{"1015":"ЗА"},{"1009":"ЗА"},{"1006":"НЕ ГОЛОСУВАВ"},{"1025":"ВІДСУТНІЙ"},{"1030":"ЗА"},{"1034":"ЗА"},{"1017":"ЗА"},{"1035":"ВІДСУТНІЙ"},{"1003":"ЗА"},{"1026":"ЗА"},{"1010":"ЗА"},{"1018":"ВІДСУТНІЙ"},{"1001":"ЗА"},{"1019":"ЗА"},{"1007":"ЗА"},{"1011":"ЗА"},{"1020":"ЗА"},{"1005":"ЗА"},{"1021":"ЗА"},{"1024":"ЗА"},{"1002":"ЗА"},{"1027":"ЗА"},{"1014":"ЗА"},{"1036":"ЗА"}],"voteTimestamp":"20.10.17 11:55:27"},{"voteName":"Про затвердження матеріалів проектів землеустрою щодо відведення земельних ділянок та технічної документації з землеустрою щодо встановлення меж земельної ділянки в натурі (на місцевості) та передачу у власність та постійне користування земельних ділянок","namedVoting":[{"1016":"ЗА"},{"1023":"ЗА"},{"1031":"ЗА"},{"1033":"ЗА"},{"1012":"ЗА"},{"1013":"ЗА"},{"1037":"ЗА"},{"1022":"УТРИМАВСЯ"},{"1004":"ЗА"},{"1028":"НЕ ГОЛОСУВАВ"},{"1032":"НЕ ГОЛОСУВАВ"},{"1029":"ЗА"},{"1015":"ЗА"},{"1009":"ЗА"},{"1006":"НЕ ГОЛОСУВАВ"},{"1025":"ВІДСУТНІЙ"},{"1030":"ЗА"},{"1034":"ЗА"},{"1017":"ЗА"},{"1035":"ВІДСУТНІЙ"},{"1003":"ЗА"},{"1026":"ЗА"},{"1010":"ЗА"},{"1018":"ВІДСУТНІЙ"},{"1001":"ЗА"},{"1019":"ЗА"},{"1007":"ЗА"},{"1011":"ЗА"},{"1020":"ЗА"},{"1005":"ЗА"},{"1021":"ЗА"},{"1024":"ЗА"},{"1002":"ЗА"},{"1027":"ЗА"},{"1014":"ЗА"},{"1036":"ЗА"}],"voteTimestamp":"20.10.17 11:56:35"},{"voteName":" За поправку до № 4.9. від 20.10.17 Про затвердження матеріалів проектів землеустрою щодо відведення земельних ділянок та технічної документації з землеустрою щодо встановлення меж земельної ділянки в натурі (на місцевості) та передачу у власність та постійне користування земельних ділянок; прпозиція: доповнити дане рішення: Белз та Слобода","namedVoting":[{"1016":"ЗА"},{"1023":"ЗА"},{"1031":"ЗА"},{"1033":"ЗА"},{"1012":"НЕ ГОЛОСУВАВ"},{"1013":"ЗА"},{"1037":"ЗА"},{"1022":"НЕ ГОЛОСУВАВ"},{"1004":"ЗА"},{"1028":"НЕ ГОЛОСУВАВ"},{"1032":"НЕ ГОЛОСУВАВ"},{"1029":"ЗА"},{"1015":"ЗА"},{"1009":"ЗА"},{"1006":"НЕ ГОЛОСУВАВ"},{"1025":"ВІДСУТНІЙ"},{"1030":"ЗА"},{"1034":"ЗА"},{"1017":"НЕ ГОЛОСУВАВ"},{"1035":"ВІДСУТНІЙ"},{"1003":"ЗА"},{"1026":"ЗА"},{"1010":"НЕ ГОЛОСУВАВ"},{"1018":"ВІДСУТНІЙ"},{"1001":"ЗА"},{"1019":"ЗА"},{"1007":"ЗА"},{"1011":"НЕ ГОЛОСУВАВ"},{"1020":"ЗА"},{"1005":"ЗА"},{"1021":"ЗА"},{"1024":"ЗА"},{"1002":"ЗА"},{"1027":"ЗА"},{"1014":"НЕ ГОЛОСУВАВ"},{"1036":"ЗА"}],"voteTimestamp":"20.10.17 11:57:47"},{"voteName":"Про затвердження матеріалів проектів землеустрою щодо відведення земельних ділянок та технічної документації з землеустрою щодо встановлення меж земельної ділянки в натурі (на місцевості) та передачу у власність та постійне користування земельних ділянок","namedVoting":[{"1016":"ЗА"},{"1023":"ЗА"},{"1031":"НЕ ГОЛОСУВАВ"},{"1033":"ЗА"},{"1012":"ЗА"},{"1013":"ЗА"},{"1037":"ЗА"},{"1022":"ЗА"},{"1004":"ЗА"},{"1028":"НЕ ГОЛОСУВАВ"},{"1032":"НЕ ГОЛОСУВАВ"},{"1029":"ЗА"},{"1015":"ЗА"},{"1009":"ЗА"},{"1006":"НЕ ГОЛОСУВАВ"},{"1025":"ВІДСУТНІЙ"},{"1030":"ЗА"},{"1034":"ЗА"},{"1017":"ЗА"},{"1035":"ВІДСУТНІЙ"},{"1003":"ЗА"},{"1026":"ЗА"},{"1010":"НЕ ГОЛОСУВАВ"},{"1018":"ВІДСУТНІЙ"},{"1001":"ЗА"},{"1019":"ЗА"},{"1007":"ЗА"},{"1011":"ЗА"},{"1020":"ЗА"},{"1005":"ЗА"},{"1021":"ЗА"},{"1024":"ЗА"},{"1002":"ЗА"},{"1027":"ЗА"},{"1014":"ЗА"},{"1036":"ЗА"}],"voteTimestamp":"20.10.17 11:58:31"},{"voteName":"Про надання дозволу на розроблення проектів землеустрою щодо відведення земельних ділянок під об'єктами нерухомого майна","namedVoting":[{"1016":"ЗА"},{"1023":"ЗА"},{"1031":"ЗА"},{"1033":"ЗА"},{"1012":"ЗА"},{"1013":"ЗА"},{"1037":"ЗА"},{"1022":"НЕ ГОЛОСУВАВ"},{"1004":"ЗА"},{"1028":"НЕ ГОЛОСУВАВ"},{"1032":"ЗА"},{"1029":"ЗА"},{"1015":"ЗА"},{"1009":"ЗА"},{"1006":"НЕ ГОЛОСУВАВ"},{"1025":"ВІДСУТНІЙ"},{"1030":"ЗА"},{"1034":"ЗА"},{"1017":"ЗА"},{"1035":"ВІДСУТНІЙ"},{"1003":"ЗА"},{"1026":"ЗА"},{"1010":"ЗА"},{"1018":"ВІДСУТНІЙ"},{"1001":"ЗА"},{"1019":"ЗА"},{"1007":"ЗА"},{"1011":"ЗА"},{"1020":"ЗА"},{"1005":"ЗА"},{"1021":"ЗА"},{"1024":"ЗА"},{"1002":"ЗА"},{"1027":"ЗА"},{"1014":"ЗА"},{"1036":"ЗА"}],"voteTimestamp":"20.10.17 11:59:07"},{"voteName":" За поправку до № 4.10 від 20.10.17 Про надання дозволу на розроблення проектів землеустрою щодо відведення земельних ділянок під","namedVoting":[{"1016":"ЗА"},{"1023":"ЗА"},{"1031":"ЗА"},{"1033":"ЗА"},{"1012":"ЗА"},{"1013":"ЗА"},{"1037":"ЗА"},{"1022":"ЗА"},{"1004":"ЗА"},{"1028":"ЗА"},{"1032":"НЕ ГОЛОСУВАВ"},{"1029":"ЗА"},{"1015":"ЗА"},{"1009":"ЗА"},{"1006":"ЗА"},{"1025":"ВІДСУТНІЙ"},{"1030":"ЗА"},{"1034":"ЗА"},{"1017":"НЕ ГОЛОСУВАВ"},{"1035":"ВІДСУТНІЙ"},{"1003":"ЗА"},{"1026":"ЗА"},{"1010":"ЗА"},{"1018":"ВІДСУТНІЙ"},{"1001":"ЗА"},{"1019":"ЗА"},{"1007":"ЗА"},{"1011":"ЗА"},{"1020":"ЗА"},{"1005":"ЗА"},{"1021":"ЗА"},{"1024":"ЗА"},{"1002":"ЗА"},{"1027":"ЗА"},{"1014":"ЗА"},{"1036":"ЗА"}],"voteTimestamp":"20.10.17 12:00:38"},{"voteName":" За поправку до № 4.10 від 20.10.17 Про надання дозволу на розроблення проектів землеустрою щодо відведення земельних ділянок під","namedVoting":[{"1016":"ЗА"},{"1023":"ЗА"},{"1031":"ЗА"},{"1033":"ЗА"},{"1012":"ЗА"},{"1013":"ЗА"},{"1037":"ЗА"},{"1022":"ЗА"},{"1004":"НЕ ГОЛОСУВАВ"},{"1028":"ЗА"},{"1032":"ЗА"},{"1029":"НЕ ГОЛОСУВАВ"},{"1015":"ЗА"},{"1009":"ЗА"},{"1006":"НЕ ГОЛОСУВАВ"},{"1025":"ВІДСУТНІЙ"},{"1030":"ЗА"},{"1034":"ЗА"},{"1017":"НЕ ГОЛОСУВАВ"},{"1035":"ВІДСУТНІЙ"},{"1003":"ЗА"},{"1026":"ЗА"},{"1010":"НЕ ГОЛОСУВАВ"},{"1018":"ВІДСУТНІЙ"},{"1001":"ЗА"},{"1019":"ЗА"},{"1007":"ЗА"},{"1011":"НЕ ГОЛОСУВАВ"},{"1020":"ЗА"},{"1005":"ЗА"},{"1021":"ЗА"},{"1024":"ЗА"},{"1002":"ЗА"},{"1027":"ЗА"},{"1014":"ЗА"},{"1036":"ЗА"}],"voteTimestamp":"20.10.17 12:01:46"},{"voteName":" За поправку до № 4.10 від 20.10.17 Про надання дозволу на розроблення проектів землеустрою щодо відведення земельних ділянок під об'єктами нерухомого майна; пропозиція: п.п. 1.7 (Т.Попадинець) зняти з розгляду","namedVoting":[{"1016":"ЗА"},{"1023":"ЗА"},{"1031":"ЗА"},{"1033":"ЗА"},{"1012":"ЗА"},{"1013":"УТРИМАВСЯ"},{"1037":"ЗА"},{"1022":"ЗА"},{"1004":"ЗА"},{"1028":"ЗА"},{"1032":"ЗА"},{"1029":"ЗА"},{"1015":"ЗА"},{"1009":"ЗА"},{"1006":"ЗА"},{"1025":"ВІДСУТНІЙ"},{"1030":"ЗА"},{"1034":"ЗА"},{"1017":"ЗА"},{"1035":"ВІДСУТНІЙ"},{"1003":"ЗА"},{"1026":"ЗА"},{"1010":"ЗА"},{"1018":"ВІДСУТНІЙ"},{"1001":"ЗА"},{"1019":"ЗА"},{"1007":"ЗА"},{"1011":"ЗА"},{"1020":"ЗА"},{"1005":"ЗА"},{"1021":"ЗА"},{"1024":"НЕ ГОЛОСУВАВ"},{"1002":"ЗА"},{"1027":"ЗА"},{"1014":"ЗА"},{"1036":"НЕ ГОЛОСУВАВ"}],"voteTimestamp":"20.10.17 12:04:20"},{"voteName":"Про надання дозволу на розроблення проектів землеустрою щодо відведення земельних ділянок під об'єктами нерухомого майна","namedVoting":[{"1016":"ЗА"},{"1023":"ЗА"},{"1031":"ЗА"},{"1033":"ЗА"},{"1012":"НЕ ГОЛОСУВАВ"},{"1013":"ЗА"},{"1037":"ЗА"},{"1022":"ЗА"},{"1004":"ЗА"},{"1028":"НЕ ГОЛОСУВАВ"},{"1032":"ЗА"},{"1029":"ЗА"},{"1015":"ЗА"},{"1009":"ЗА"},{"1006":"НЕ ГОЛОСУВАВ"},{"1025":"ВІДСУТНІЙ"},{"1030":"ЗА"},{"1034":"ЗА"},{"1017":"ЗА"},{"1035":"ВІДСУТНІЙ"},{"1003":"ЗА"},{"1026":"ЗА"},{"1010":"НЕ ГОЛОСУВАВ"},{"1018":"ВІДСУТНІЙ"},{"1001":"ЗА"},{"1019":"ЗА"},{"1007":"ЗА"},{"1011":"ЗА"},{"1020":"ЗА"},{"1005":"ЗА"},{"1021":"ЗА"},{"1024":"ЗА"},{"1002":"ЗА"},{"1027":"ЗА"},{"1014":"ЗА"},{"1036":"ЗА"}],"voteTimestamp":"20.10.17 12:05:27"},{"voteName":"Про надання дозволу на розроблення проектів землеустрою щодо відведення земельних ділянок для будівництва та обслуговування житлових будинків","namedVoting":[{"1016":"ЗА"},{"1023":"ЗА"},{"1031":"ЗА"},{"1033":"ЗА"},{"1012":"НЕ ГОЛОСУВАВ"},{"1013":"ЗА"},{"1037":"ЗА"},{"1022":"ЗА"},{"1004":"ЗА"},{"1028":"ЗА"},{"1032":"НЕ ГОЛОСУВАВ"},{"1029":"ЗА"},{"1015":"УТРИМАВСЯ"},{"1009":"ЗА"},{"1006":"НЕ ГОЛОСУВАВ"},{"1025":"ВІДСУТНІЙ"},{"1030":"ЗА"},{"1034":"ЗА"},{"1017":"ЗА"},{"1035":"ВІДСУТНІЙ"},{"1003":"ЗА"},{"1026":"ЗА"},{"1010":"НЕ ГОЛОСУВАВ"},{"1018":"ВІДСУТНІЙ"},{"1001":"ЗА"},{"1019":"ЗА"},{"1007":"ЗА"},{"1011":"НЕ ГОЛОСУВАВ"},{"1020":"НЕ ГОЛОСУВАВ"},{"1005":"ЗА"},{"1021":"ЗА"},{"1024":"ЗА"},{"1002":"ЗА"},{"1027":"ЗА"},{"1014":"ЗА"},{"1036":"ЗА"}],"voteTimestamp":"20.10.17 12:06:07"},{"voteName":"Про припинення права користування земельною ділянкою","namedVoting":[{"1016":"ЗА"},{"1023":"ЗА"},{"1031":"ЗА"},{"1033":"ЗА"},{"1012":"НЕ ГОЛОСУВАВ"},{"1013":"ЗА"},{"1037":"ЗА"},{"1022":"ЗА"},{"1004":"ЗА"},{"1028":"ЗА"},{"1032":"ЗА"},{"1029":"ЗА"},{"1015":"ЗА"},{"1009":"ЗА"},{"1006":"НЕ ГОЛОСУВАВ"},{"1025":"ВІДСУТНІЙ"},{"1030":"ЗА"},{"1034":"ЗА"},{"1017":"ЗА"},{"1035":"ВІДСУТНІЙ"},{"1003":"ЗА"},{"1026":"ЗА"},{"1010":"НЕ ГОЛОСУВАВ"},{"1018":"ВІДСУТНІЙ"},{"1001":"ЗА"},{"1019":"ЗА"},{"1007":"ЗА"},{"1011":"ЗА"},{"1020":"ЗА"},{"1005":"ЗА"},{"1021":"ЗА"},{"1024":"ЗА"},{"1002":"ЗА"},{"1027":"ЗА"},{"1014":"ЗА"},{"1036":"ЗА"}],"voteTimestamp":"20.10.17 12:06:42"},{"voteName":"Про надання дозволу на розроблення проектів землеустрою щодо відведення земельних ділянок для будівництва та обслуговування гаражів","namedVoting":[{"1016":"ЗА"},{"1023":"УТРИМАВСЯ"},{"1031":"ЗА"},{"1033":"НЕ ГОЛОСУВАВ"},{"1012":"ЗА"},{"1013":"ЗА"},{"1037":"НЕ ГОЛОСУВАВ"},{"1022":"ЗА"},{"1004":"ЗА"},{"1028":"НЕ ГОЛОСУВАВ"},{"1032":"НЕ ГОЛОСУВАВ"},{"1029":"НЕ ГОЛОСУВАВ"},{"1015":"ЗА"},{"1009":"ЗА"},{"1006":"НЕ ГОЛОСУВАВ"},{"1025":"ВІДСУТНІЙ"},{"1030":"ЗА"},{"1034":"НЕ ГОЛОСУВАВ"},{"1017":"ЗА"},{"1035":"ВІДСУТНІЙ"},{"1003":"НЕ ГОЛОСУВАВ"},{"1026":"ЗА"},{"1010":"НЕ ГОЛОСУВАВ"},{"1018":"ВІДСУТНІЙ"},{"1001":"УТРИМАВСЯ"},{"1019":"ЗА"},{"1007":"ЗА"},{"1011":"НЕ ГОЛОСУВАВ"},{"1020":"ЗА"},{"1005":"ЗА"},{"1021":"ЗА"},{"1024":"НЕ ГОЛОСУВАВ"},{"1002":"ЗА"},{"1027":"ЗА"},{"1014":"НЕ ГОЛОСУВАВ"},{"1036":"НЕ ГОЛОСУВАВ"}],"voteTimestamp":"20.10.17 12:08:30"},{"voteName":"Про продовження терміну дії рішень міської ради","namedVoting":[{"1016":"ЗА"},{"1023":"ЗА"},{"1031":"НЕ ГОЛОСУВАВ"},{"1033":"ЗА"},{"1012":"НЕ ГОЛОСУВАВ"},{"1013":"ЗА"},{"1037":"НЕ ГОЛОСУВАВ"},{"1022":"ЗА"},{"1004":"ЗА"},{"1028":"НЕ ГОЛОСУВАВ"},{"1032":"ЗА"},{"1029":"НЕ ГОЛОСУВАВ"},{"1015":"ЗА"},{"1009":"ЗА"},{"1006":"НЕ ГОЛОСУВАВ"},{"1025":"ВІДСУТНІЙ"},{"1030":"ЗА"},{"1034":"НЕ ГОЛОСУВАВ"},{"1017":"ЗА"},{"1035":"ВІДСУТНІЙ"},{"1003":"НЕ ГОЛОСУВАВ"},{"1026":"ЗА"},{"1010":"ЗА"},{"1018":"ВІДСУТНІЙ"},{"1001":"ЗА"},{"1019":"ЗА"},{"1007":"НЕ ГОЛОСУВАВ"},{"1011":"ЗА"},{"1020":"ЗА"},{"1005":"ЗА"},{"1021":"ЗА"},{"1024":"ЗА"},{"1002":"ЗА"},{"1027":"НЕ ГОЛОСУВАВ"},{"1014":"НЕ ГОЛОСУВАВ"},{"1036":"ЗА"}],"voteTimestamp":"20.10.17 12:09:33"},{"voteName":"За поправку до № 4.14. від 20.10.17 Про продовження терміну дії рішень міської ради; пропозиція: зняти з розгляду п. 2, п.п. 2.1 (В.Бішко)  та довивчити","namedVoting":[{"1016":"ЗА"},{"1023":"ЗА"},{"1031":"ЗА"},{"1033":"НЕ ГОЛОСУВАВ"},{"1012":"ЗА"},{"1013":"ЗА"},{"1037":"ЗА"},{"1022":"НЕ ГОЛОСУВАВ"},{"1004":"НЕ ГОЛОСУВАВ"},{"1028":"ЗА"},{"1032":"ЗА"},{"1029":"ВІДСУТНІЙ"},{"1015":"ЗА"},{"1009":"НЕ ГОЛОСУВАВ"},{"1006":"ЗА"},{"1025":"ВІДСУТНІЙ"},{"1030":"ЗА"},{"1034":"ЗА"},{"1017":"НЕ ГОЛОСУВАВ"},{"1035":"ВІДСУТНІЙ"},{"1003":"НЕ ГОЛОСУВАВ"},{"1026":"НЕ ГОЛОСУВАВ"},{"1010":"ЗА"},{"1018":"ВІДСУТНІЙ"},{"1001":"ЗА"},{"1019":"НЕ ГОЛОСУВАВ"},{"1007":"ЗА"},{"1011":"ЗА"},{"1020":"ЗА"},{"1005":"ЗА"},{"1021":"ЗА"},{"1024":"НЕ ГОЛОСУВАВ"},{"1002":"ЗА"},{"1027":"ЗА"},{"1014":"ЗА"},{"1036":"НЕ ГОЛОСУВАВ"}],"voteTimestamp":"20.10.17 12:34:14"},{"voteName":"Про продовження терміну дії рішень міської ради","namedVoting":[{"1016":"ЗА"},{"1023":"ЗА"},{"1031":"ЗА"},{"1033":"НЕ ГОЛОСУВАВ"},{"1012":"ЗА"},{"1013":"ЗА"},{"1037":"ЗА"},{"1022":"ЗА"},{"1004":"ЗА"},{"1028":"НЕ ГОЛОСУВАВ"},{"1032":"ЗА"},{"1029":"НЕ ГОЛОСУВАВ"},{"1015":"ЗА"},{"1009":"ЗА"},{"1006":"ЗА"},{"1025":"ВІДСУТНІЙ"},{"1030":"ЗА"},{"1034":"ЗА"},{"1017":"НЕ ГОЛОСУВАВ"},{"1035":"ВІДСУТНІЙ"},{"1003":"ЗА"},{"1026":"ЗА"},{"1010":"НЕ ГОЛОСУВАВ"},{"1018":"ВІДСУТНІЙ"},{"1001":"ЗА"},{"1019":"ЗА"},{"1007":"ЗА"},{"1011":"НЕ ГОЛОСУВАВ"},{"1020":"ЗА"},{"1005":"ЗА"},{"1021":"ЗА"},{"1024":"ЗА"},{"1002":"ЗА"},{"1027":"НЕ ГОЛОСУВАВ"},{"1014":"ЗА"},{"1036":"ЗА"}],"voteTimestamp":"20.10.17 12:35:08"},{"voteName":"змінити порядок голосування та розглянути  додатково включені проекти рішень, що стосуються земельних питань","namedVoting":[{"1016":"ЗА"},{"1023":"ЗА"},{"1031":"НЕ ГОЛОСУВАВ"},{"1033":"НЕ ГОЛОСУВАВ"},{"1012":"НЕ ГОЛОСУВАВ"},{"1013":"ЗА"},{"1037":"ЗА"},{"1022":"ЗА"},{"1004":"ЗА"},{"1028":"ЗА"},{"1032":"ЗА"},{"1029":"ВІДСУТНІЙ"},{"1015":"ЗА"},{"1009":"ЗА"},{"1006":"НЕ ГОЛОСУВАВ"},{"1025":"ВІДСУТНІЙ"},{"1030":"ЗА"},{"1034":"ЗА"},{"1017":"ЗА"},{"1035":"ВІДСУТНІЙ"},{"1003":"ЗА"},{"1026":"ЗА"},{"1010":"ЗА"},{"1018":"ВІДСУТНІЙ"},{"1001":"ЗА"},{"1019":"ЗА"},{"1007":"ЗА"},{"1011":"ЗА"},{"1020":"ЗА"},{"1005":"ЗА"},{"1021":"ЗА"},{"1024":"НЕ ГОЛОСУВАВ"},{"1002":"ЗА"},{"1027":"ЗА"},{"1014":"ЗА"},{"1036":"НЕ ГОЛОСУВАВ"}],"voteTimestamp":"20.10.17 12:36:05"},{"voteName":"Про надання дозволу на розроблення проекту землеустрою щодо відведення земельної ділянки обслуговування багатоквартирного житлового будинку","namedVoting":[{"1016":"ЗА"},{"1023":"ЗА"},{"1031":"ЗА"},{"1033":"НЕ ГОЛОСУВАВ"},{"1012":"ЗА"},{"1013":"ЗА"},{"1037":"ЗА"},{"1022":"ЗА"},{"1004":"ЗА"},{"1028":"НЕ ГОЛОСУВАВ"},{"1032":"ЗА"},{"1029":"ВІДСУТНІЙ"},{"1015":"ЗА"},{"1009":"ЗА"},{"1006":"ЗА"},{"1025":"ВІДСУТНІЙ"},{"1030":"ЗА"},{"1034":"ЗА"},{"1017":"ЗА"},{"1035":"ВІДСУТНІЙ"},{"1003":"НЕ ГОЛОСУВАВ"},{"1026":"ЗА"},{"1010":"ЗА"},{"1018":"ВІДСУТНІЙ"},{"1001":"ЗА"},{"1019":"НЕ ГОЛОСУВАВ"},{"1007":"ЗА"},{"1011":"ЗА"},{"1020":"ЗА"},{"1005":"ЗА"},{"1021":"ЗА"},{"1024":"ЗА"},{"1002":"ЗА"},{"1027":"ЗА"},{"1014":"ЗА"},{"1036":"НЕ ГОЛОСУВАВ"}],"voteTimestamp":"20.10.17 12:37:29"},{"voteName":"Про продовження терміну дії рішення міської ради від 31.01.2014 року № 1241","namedVoting":[{"1016":"ЗА"},{"1023":"ЗА"},{"1031":"ЗА"},{"1033":"НЕ ГОЛОСУВАВ"},{"1012":"ЗА"},{"1013":"ЗА"},{"1037":"ЗА"},{"1022":"ЗА"},{"1004":"ЗА"},{"1028":"НЕ ГОЛОСУВАВ"},{"1032":"ЗА"},{"1029":"ВІДСУТНІЙ"},{"1015":"ЗА"},{"1009":"ЗА"},{"1006":"ЗА"},{"1025":"ВІДСУТНІЙ"},{"1030":"ЗА"},{"1034":"ЗА"},{"1017":"ЗА"},{"1035":"ВІДСУТНІЙ"},{"1003":"ЗА"},{"1026":"ЗА"},{"1010":"ЗА"},{"1018":"ВІДСУТНІЙ"},{"1001":"НЕ ГОЛОСУВАВ"},{"1019":"НЕ ГОЛОСУВАВ"},{"1007":"ЗА"},{"1011":"ЗА"},{"1020":"ЗА"},{"1005":"ЗА"},{"1021":"ЗА"},{"1024":"ЗА"},{"1002":"ЗА"},{"1027":"ЗА"},{"1014":"НЕ ГОЛОСУВАВ"},{"1036":"ЗА"}],"voteTimestamp":"20.10.17 12:38:11"},{"voteName":"Про затвердження проекту землеустрою щодо відведення земельної ділянки, площею 0,2050га по вул. Грінченка, включеної в перелік для продажу на земельних торгах у формі аукціону та надання дозволу на виготовлення звіту про експертну грошову оцінку","namedVoting":[{"1016":"ЗА"},{"1023":"ЗА"},{"1031":"ЗА"},{"1033":"НЕ ГОЛОСУВАВ"},{"1012":"НЕ ГОЛОСУВАВ"},{"1013":"ЗА"},{"1037":"ЗА"},{"1022":"ЗА"},{"1004":"ЗА"},{"1028":"НЕ ГОЛОСУВАВ"},{"1032":"ЗА"},{"1029":"ВІДСУТНІЙ"},{"1015":"ЗА"},{"1009":"ЗА"},{"1006":"НЕ ГОЛОСУВАВ"},{"1025":"ВІДСУТНІЙ"},{"1030":"ЗА"},{"1034":"ЗА"},{"1017":"ЗА"},{"1035":"ВІДСУТНІЙ"},{"1003":"ЗА"},{"1026":"ЗА"},{"1010":"ЗА"},{"1018":"ВІДСУТНІЙ"},{"1001":"НЕ ГОЛОСУВАВ"},{"1019":"НЕ ГОЛОСУВАВ"},{"1007":"ЗА"},{"1011":"ЗА"},{"1020":"ЗА"},{"1005":"ЗА"},{"1021":"ЗА"},{"1024":"ЗА"},{"1002":"НЕ ГОЛОСУВАВ"},{"1027":"ЗА"},{"1014":"НЕ ГОЛОСУВАВ"},{"1036":"ЗА"}],"voteTimestamp":"20.10.17 12:39:10"},{"voteName":"Про внесення змін до Положення про громадський бюджет м. Дрогобича, затвердженого рішенням сесії Дрогобицької міської ради № 479 від 30.11.2016 року","namedVoting":[{"1016":"ЗА"},{"1023":"ЗА"},{"1031":"ЗА"},{"1033":"НЕ ГОЛОСУВАВ"},{"1012":"ЗА"},{"1013":"ЗА"},{"1037":"ЗА"},{"1022":"ЗА"},{"1004":"ЗА"},{"1028":"НЕ ГОЛОСУВАВ"},{"1032":"ЗА"},{"1029":"ВІДСУТНІЙ"},{"1015":"ЗА"},{"1009":"ЗА"},{"1006":"ЗА"},{"1025":"ВІДСУТНІЙ"},{"1030":"ЗА"},{"1034":"ЗА"},{"1017":"ЗА"},{"1035":"ВІДСУТНІЙ"},{"1003":"ЗА"},{"1026":"ЗА"},{"1010":"ЗА"},{"1018":"ВІДСУТНІЙ"},{"1001":"НЕ ГОЛОСУВАВ"},{"1019":"НЕ ГОЛОСУВАВ"},{"1007":"ЗА"},{"1011":"ЗА"},{"1020":"ЗА"},{"1005":"ЗА"},{"1021":"ЗА"},{"1024":"ЗА"},{"1002":"ЗА"},{"1027":"ЗА"},{"1014":"ЗА"},{"1036":"ЗА"}],"voteTimestamp":"20.10.17 12:42:29"},{"voteName":"За поправку до № 5 від 20.10.17 Про внесення змін до Положення про громадський бюджет ","namedVoting":[{"1016":"УТРИМАВСЯ"},{"1023":"ЗА"},{"1031":"НЕ ГОЛОСУВАВ"},{"1033":"НЕ ГОЛОСУВАВ"},{"1012":"ЗА"},{"1013":"НЕ ГОЛОСУВАВ"},{"1037":"НЕ ГОЛОСУВАВ"},{"1022":"НЕ ГОЛОСУВАВ"},{"1004":"НЕ ГОЛОСУВАВ"},{"1028":"НЕ ГОЛОСУВАВ"},{"1032":"НЕ ГОЛОСУВАВ"},{"1029":"ВІДСУТНІЙ"},{"1015":"НЕ ГОЛОСУВАВ"},{"1009":"НЕ ГОЛОСУВАВ"},{"1006":"ЗА"},{"1025":"ВІДСУТНІЙ"},{"1030":"ЗА"},{"1034":"НЕ ГОЛОСУВАВ"},{"1017":"НЕ ГОЛОСУВАВ"},{"1035":"ВІДСУТНІЙ"},{"1003":"НЕ ГОЛОСУВАВ"},{"1026":"НЕ ГОЛОСУВАВ"},{"1010":"НЕ ГОЛОСУВАВ"},{"1018":"ВІДСУТНІЙ"},{"1001":"ЗА"},{"1019":"НЕ ГОЛОСУВАВ"},{"1007":"НЕ ГОЛОСУВАВ"},{"1011":"НЕ ГОЛОСУВАВ"},{"1020":"НЕ ГОЛОСУВАВ"},{"1005":"НЕ ГОЛОСУВАВ"},{"1021":"ЗА"},{"1024":"ЗА"},{"1002":"ЗА"},{"1027":"НЕ ГОЛОСУВАВ"},{"1014":"НЕ ГОЛОСУВАВ"},{"1036":"НЕ ГОЛОСУВАВ"}],"voteTimestamp":"20.10.17 12:46:59"},{"voteName":" За поправку до № 5 від 20.10.17 Про внесення змін до Положення про громадський бюджет м. Дрогобича, затвердженого рішенням сесії Дрогобицької міської ради № 479 від 30.11.2016 року; пропозиція: вилучити з усього тексту слово «працюючих»","namedVoting":[{"1016":"НЕ ГОЛОСУВАВ"},{"1023":"НЕ ГОЛОСУВАВ"},{"1031":"НЕ ГОЛОСУВАВ"},{"1033":"НЕ ГОЛОСУВАВ"},{"1012":"ЗА"},{"1013":"НЕ ГОЛОСУВАВ"},{"1037":"НЕ ГОЛОСУВАВ"},{"1022":"НЕ ГОЛОСУВАВ"},{"1004":"ПРОТИ"},{"1028":"НЕ ГОЛОСУВАВ"},{"1032":"НЕ ГОЛОСУВАВ"},{"1029":"НЕ ГОЛОСУВАВ"},{"1015":"ЗА"},{"1009":"НЕ ГОЛОСУВАВ"},{"1006":"ЗА"},{"1025":"ВІДСУТНІЙ"},{"1030":"НЕ ГОЛОСУВАВ"},{"1034":"НЕ ГОЛОСУВАВ"},{"1017":"НЕ ГОЛОСУВАВ"},{"1035":"ВІДСУТНІЙ"},{"1003":"ЗА"},{"1026":"НЕ ГОЛОСУВАВ"},{"1010":"ПРОТИ"},{"1018":"ВІДСУТНІЙ"},{"1001":"НЕ ГОЛОСУВАВ"},{"1019":"НЕ ГОЛОСУВАВ"},{"1007":"НЕ ГОЛОСУВАВ"},{"1011":"НЕ ГОЛОСУВАВ"},{"1020":"ПРОТИ"},{"1005":"ЗА"},{"1021":"ПРОТИ"},{"1024":"НЕ ГОЛОСУВАВ"},{"1002":"ЗА"},{"1027":"НЕ ГОЛОСУВАВ"},{"1014":"ПРОТИ"},{"1036":"НЕ ГОЛОСУВАВ"}],"voteTimestamp":"20.10.17 12:49:23"},{"voteName":"Про внесення змін до Положення про громадський бюджет м. Дрогобича, затвердженого рішенням сесії Дрогобицької міської ради № 479 від 30.11.2016 року","namedVoting":[{"1016":"ЗА"},{"1023":"ЗА"},{"1031":"ЗА"},{"1033":"НЕ ГОЛОСУВАВ"},{"1012":"ЗА"},{"1013":"НЕ ГОЛОСУВАВ"},{"1037":"ЗА"},{"1022":"ЗА"},{"1004":"ЗА"},{"1028":"НЕ ГОЛОСУВАВ"},{"1032":"ЗА"},{"1029":"ВІДСУТНІЙ"},{"1015":"ЗА"},{"1009":"ЗА"},{"1006":"ЗА"},{"1025":"ВІДСУТНІЙ"},{"1030":"ЗА"},{"1034":"ЗА"},{"1017":"ЗА"},{"1035":"ВІДСУТНІЙ"},{"1003":"ЗА"},{"1026":"ЗА"},{"1010":"ЗА"},{"1018":"ВІДСУТНІЙ"},{"1001":"ЗА"},{"1019":"ЗА"},{"1007":"ЗА"},{"1011":"ЗА"},{"1020":"ЗА"},{"1005":"ЗА"},{"1021":"ЗА"},{"1024":"ЗА"},{"1002":"НЕ ГОЛОСУВАВ"},{"1027":"НЕ ГОЛОСУВАВ"},{"1014":"ЗА"},{"1036":"ЗА"}],"voteTimestamp":"20.10.17 12:50:00"},{"voteName":"Про внесення доповнення до Положення про порядок встановлення пам'ятних знаків, меморіальних та анотаційних дощок у місті Дрогобичі","namedVoting":[{"1016":"ЗА"},{"1023":"ЗА"},{"1031":"ЗА"},{"1033":"НЕ ГОЛОСУВАВ"},{"1012":"НЕ ГОЛОСУВАВ"},{"1013":"ЗА"},{"1037":"ЗА"},{"1022":"ЗА"},{"1004":"ЗА"},{"1028":"НЕ ГОЛОСУВАВ"},{"1032":"ЗА"},{"1029":"ВІДСУТНІЙ"},{"1015":"ЗА"},{"1009":"ЗА"},{"1006":"ЗА"},{"1025":"ВІДСУТНІЙ"},{"1030":"ЗА"},{"1034":"ЗА"},{"1017":"ЗА"},{"1035":"ВІДСУТНІЙ"},{"1003":"ЗА"},{"1026":"ЗА"},{"1010":"ЗА"},{"1018":"ВІДСУТНІЙ"},{"1001":"ЗА"},{"1019":"ЗА"},{"1007":"НЕ ГОЛОСУВАВ"},{"1011":"ЗА"},{"1020":"ЗА"},{"1005":"ЗА"},{"1021":"НЕ ГОЛОСУВАВ"},{"1024":"ЗА"},{"1002":"ЗА"},{"1027":"НЕ ГОЛОСУВАВ"},{"1014":"ЗА"},{"1036":"НЕ ГОЛОСУВАВ"}],"voteTimestamp":"20.10.17 12:52:28"},{"voteName":"Про внесення змін в кількісний та персональний склад постійних комісій Дрогобицької міської ради","namedVoting":[{"1016":"ЗА"},{"1023":"ЗА"},{"1031":"ЗА"},{"1033":"НЕ ГОЛОСУВАВ"},{"1012":"ЗА"},{"1013":"ЗА"},{"1037":"ЗА"},{"1022":"НЕ ГОЛОСУВАВ"},{"1004":"ЗА"},{"1028":"ЗА"},{"1032":"ЗА"},{"1029":"ВІДСУТНІЙ"},{"1015":"ЗА"},{"1009":"ЗА"},{"1006":"ЗА"},{"1025":"ВІДСУТНІЙ"},{"1030":"ЗА"},{"1034":"ЗА"},{"1017":"ЗА"},{"1035":"ВІДСУТНІЙ"},{"1003":"ЗА"},{"1026":"ЗА"},{"1010":"ЗА"},{"1018":"ВІДСУТНІЙ"},{"1001":"ЗА"},{"1019":"ЗА"},{"1007":"ЗА"},{"1011":"ЗА"},{"1020":"ЗА"},{"1005":"ЗА"},{"1021":"НЕ ГОЛОСУВАВ"},{"1024":"ЗА"},{"1002":"ЗА"},{"1027":"НЕ ГОЛОСУВАВ"},{"1014":"ЗА"},{"1036":"НЕ ГОЛОСУВАВ"}],"voteTimestamp":"20.10.17 12:53:39"},{"voteName":"За поправку до № 7 від 20.10.17 Про внесення змін в кількісний та персональний склад постійних комісій Дрогобицької міської ради; пропозиція: провести голосування по кожному пунктові та підпунктові окремо","namedVoting":[{"1016":"ЗА"},{"1023":"ЗА"},{"1031":"ЗА"},{"1033":"НЕ ГОЛОСУВАВ"},{"1012":"ЗА"},{"1013":"ЗА"},{"1037":"ЗА"},{"1022":"НЕ ГОЛОСУВАВ"},{"1004":"ЗА"},{"1028":"ЗА"},{"1032":"ЗА"},{"1029":"ВІДСУТНІЙ"},{"1015":"ЗА"},{"1009":"ЗА"},{"1006":"ЗА"},{"1025":"ВІДСУТНІЙ"},{"1030":"НЕ ГОЛОСУВАВ"},{"1034":"ЗА"},{"1017":"НЕ ГОЛОСУВАВ"},{"1035":"ВІДСУТНІЙ"},{"1003":"ЗА"},{"1026":"НЕ ГОЛОСУВАВ"},{"1010":"ЗА"},{"1018":"ВІДСУТНІЙ"},{"1001":"ЗА"},{"1019":"ЗА"},{"1007":"ЗА"},{"1011":"ЗА"},{"1020":"ЗА"},{"1005":"ЗА"},{"1021":"ЗА"},{"1024":"ЗА"},{"1002":"ЗА"},{"1027":"НЕ ГОЛОСУВАВ"},{"1014":"ЗА"},{"1036":"НЕ ГОЛОСУВАВ"}],"voteTimestamp":"20.10.17 12:55:19"},{"voteName":"За поправку до № 7 від 20.10.17 Про внесення змін в кількісний та персональний склад постійних комісій Дрогобицької міської ради на голосування п. 1 , без слів «\u2026та обрати головою комісії.»","namedVoting":[{"1016":"НЕ ГОЛОСУВАВ"},{"1023":"НЕ ГОЛОСУВАВ"},{"1031":"ПРОТИ"},{"1033":"НЕ ГОЛОСУВАВ"},{"1012":"ЗА"},{"1013":"ЗА"},{"1037":"НЕ ГОЛОСУВАВ"},{"1022":"НЕ ГОЛОСУВАВ"},{"1004":"ЗА"},{"1028":"ЗА"},{"1032":"НЕ ГОЛОСУВАВ"},{"1029":"ВІДСУТНІЙ"},{"1015":"ЗА"},{"1009":"ЗА"},{"1006":"НЕ ГОЛОСУВАВ"},{"1025":"ВІДСУТНІЙ"},{"1030":"ЗА"},{"1034":"НЕ ГОЛОСУВАВ"},{"1017":"НЕ ГОЛОСУВАВ"},{"1035":"ВІДСУТНІЙ"},{"1003":"НЕ ГОЛОСУВАВ"},{"1026":"НЕ ГОЛОСУВАВ"},{"1010":"ЗА"},{"1018":"ВІДСУТНІЙ"},{"1001":"ПРОТИ"},{"1019":"НЕ ГОЛОСУВАВ"},{"1007":"НЕ ГОЛОСУВАВ"},{"1011":"ЗА"},{"1020":"ПРОТИ"},{"1005":"НЕ ГОЛОСУВАВ"},{"1021":"ЗА"},{"1024":"НЕ ГОЛОСУВАВ"},{"1002":"ЗА"},{"1027":"НЕ ГОЛОСУВАВ"},{"1014":"ЗА"},{"1036":"НЕ ГОЛОСУВАВ"}],"voteTimestamp":"20.10.17 12:58:19"},{"voteName":"За поправку до № 7 від 20.10.17 Про внесення змін в кількісний та персональний склад постійних комісій Дрогобицької міської ради; на голосування п.п. 2.1","namedVoting":[{"1016":"ПРОТИ"},{"1023":"ПРОТИ"},{"1031":"ПРОТИ"},{"1033":"НЕ ГОЛОСУВАВ"},{"1012":"НЕ ГОЛОСУВАВ"},{"1013":"НЕ ГОЛОСУВАВ"},{"1037":"НЕ ГОЛОСУВАВ"},{"1022":"НЕ ГОЛОСУВАВ"},{"1004":"НЕ ГОЛОСУВАВ"},{"1028":"НЕ ГОЛОСУВАВ"},{"1032":"НЕ ГОЛОСУВАВ"},{"1029":"ВІДСУТНІЙ"},{"1015":"УТРИМАВСЯ"},{"1009":"НЕ ГОЛОСУВАВ"},{"1006":"НЕ ГОЛОСУВАВ"},{"1025":"ВІДСУТНІЙ"},{"1030":"НЕ ГОЛОСУВАВ"},{"1034":"НЕ ГОЛОСУВАВ"},{"1017":"НЕ ГОЛОСУВАВ"},{"1035":"ВІДСУТНІЙ"},{"1003":"НЕ ГОЛОСУВАВ"},{"1026":"НЕ ГОЛОСУВАВ"},{"1010":"НЕ ГОЛОСУВАВ"},{"1018":"ВІДСУТНІЙ"},{"1001":"НЕ ГОЛОСУВАВ"},{"1019":"НЕ ГОЛОСУВАВ"},{"1007":"ПРОТИ"},{"1011":"НЕ ГОЛОСУВАВ"},{"1020":"ПРОТИ"},{"1005":"НЕ ГОЛОСУВАВ"},{"1021":"ПРОТИ"},{"1024":"НЕ ГОЛОСУВАВ"},{"1002":"ЗА"},{"1027":"НЕ ГОЛОСУВАВ"},{"1014":"ПРОТИ"},{"1036":"НЕ ГОЛОСУВАВ"}],"voteTimestamp":"20.10.17 13:00:13"},{"voteName":"За поправку до № 7 від 20.10.17 Про внесення змін в кількісний та персональний склад постійних комісій Дрогобицької міської ради; на голосування п.п. 2.2.","namedVoting":[{"1016":"НЕ ГОЛОСУВАВ"},{"1023":"НЕ ГОЛОСУВАВ"},{"1031":"ПРОТИ"},{"1033":"НЕ ГОЛОСУВАВ"},{"1012":"ЗА"},{"1013":"НЕ ГОЛОСУВАВ"},{"1037":"НЕ ГОЛОСУВАВ"},{"1022":"ЗА"},{"1004":"НЕ ГОЛОСУВАВ"},{"1028":"НЕ ГОЛОСУВАВ"},{"1032":"НЕ ГОЛОСУВАВ"},{"1029":"ВІДСУТНІЙ"},{"1015":"УТРИМАВСЯ"},{"1009":"НЕ ГОЛОСУВАВ"},{"1006":"НЕ ГОЛОСУВАВ"},{"1025":"ВІДСУТНІЙ"},{"1030":"НЕ ГОЛОСУВАВ"},{"1034":"ПРОТИ"},{"1017":"НЕ ГОЛОСУВАВ"},{"1035":"ВІДСУТНІЙ"},{"1003":"НЕ ГОЛОСУВАВ"},{"1026":"НЕ ГОЛОСУВАВ"},{"1010":"НЕ ГОЛОСУВАВ"},{"1018":"ВІДСУТНІЙ"},{"1001":"НЕ ГОЛОСУВАВ"},{"1019":"НЕ ГОЛОСУВАВ"},{"1007":"ПРОТИ"},{"1011":"НЕ ГОЛОСУВАВ"},{"1020":"ПРОТИ"},{"1005":"НЕ ГОЛОСУВАВ"},{"1021":"ПРОТИ"},{"1024":"НЕ ГОЛОСУВАВ"},{"1002":"ЗА"},{"1027":"НЕ ГОЛОСУВАВ"},{"1014":"ЗА"},{"1036":"НЕ ГОЛОСУВАВ"}],"voteTimestamp":"20.10.17 13:00:58"},{"voteName":"За поправку до № 7 від 20.10.17 Про внесення змін в кількісний та персональний склад постійних комісій Дрогобицької міської ради; на голосування п.п. 2.3","namedVoting":[{"1016":"НЕ ГОЛОСУВАВ"},{"1023":"НЕ ГОЛОСУВАВ"},{"1031":"ПРОТИ"},{"1033":"НЕ ГОЛОСУВАВ"},{"1012":"НЕ ГОЛОСУВАВ"},{"1013":"НЕ ГОЛОСУВАВ"},{"1037":"НЕ ГОЛОСУВАВ"},{"1022":"ЗА"},{"1004":"НЕ ГОЛОСУВАВ"},{"1028":"НЕ ГОЛОСУВАВ"},{"1032":"НЕ ГОЛОСУВАВ"},{"1029":"ВІДСУТНІЙ"},{"1015":"УТРИМАВСЯ"},{"1009":"НЕ ГОЛОСУВАВ"},{"1006":"НЕ ГОЛОСУВАВ"},{"1025":"ВІДСУТНІЙ"},{"1030":"НЕ ГОЛОСУВАВ"},{"1034":"НЕ ГОЛОСУВАВ"},{"1017":"НЕ ГОЛОСУВАВ"},{"1035":"ВІДСУТНІЙ"},{"1003":"НЕ ГОЛОСУВАВ"},{"1026":"НЕ ГОЛОСУВАВ"},{"1010":"ПРОТИ"},{"1018":"ВІДСУТНІЙ"},{"1001":"НЕ ГОЛОСУВАВ"},{"1019":"НЕ ГОЛОСУВАВ"},{"1007":"НЕ ГОЛОСУВАВ"},{"1011":"ПРОТИ"},{"1020":"НЕ ГОЛОСУВАВ"},{"1005":"НЕ ГОЛОСУВАВ"},{"1021":"ПРОТИ"},{"1024":"НЕ ГОЛОСУВАВ"},{"1002":"НЕ ГОЛОСУВАВ"},{"1027":"НЕ ГОЛОСУВАВ"},{"1014":"ПРОТИ"},{"1036":"НЕ ГОЛОСУВАВ"}],"voteTimestamp":"20.10.17 13:02:03"},{"voteName":"За поправку до № 7 від 20.10.17 Про внесення змін в кількісний та персональний склад постійних комісій Дрогобицької міської ради; на голосування п.п. 2.4","namedVoting":[{"1016":"НЕ ГОЛОСУВАВ"},{"1023":"НЕ ГОЛОСУВАВ"},{"1031":"ПРОТИ"},{"1033":"НЕ ГОЛОСУВАВ"},{"1012":"ЗА"},{"1013":"НЕ ГОЛОСУВАВ"},{"1037":"НЕ ГОЛОСУВАВ"},{"1022":"НЕ ГОЛОСУВАВ"},{"1004":"НЕ ГОЛОСУВАВ"},{"1028":"НЕ ГОЛОСУВАВ"},{"1032":"ЗА"},{"1029":"НЕ ГОЛОСУВАВ"},{"1015":"УТРИМАВСЯ"},{"1009":"НЕ ГОЛОСУВАВ"},{"1006":"НЕ ГОЛОСУВАВ"},{"1025":"ВІДСУТНІЙ"},{"1030":"ЗА"},{"1034":"НЕ ГОЛОСУВАВ"},{"1017":"НЕ ГОЛОСУВАВ"},{"1035":"ВІДСУТНІЙ"},{"1003":"НЕ ГОЛОСУВАВ"},{"1026":"НЕ ГОЛОСУВАВ"},{"1010":"НЕ ГОЛОСУВАВ"},{"1018":"ВІДСУТНІЙ"},{"1001":"ЗА"},{"1019":"НЕ ГОЛОСУВАВ"},{"1007":"УТРИМАВСЯ"},{"1011":"ПРОТИ"},{"1020":"ЗА"},{"1005":"НЕ ГОЛОСУВАВ"},{"1021":"ПРОТИ"},{"1024":"НЕ ГОЛОСУВАВ"},{"1002":"ЗА"},{"1027":"НЕ ГОЛОСУВАВ"},{"1014":"ПРОТИ"},{"1036":"НЕ ГОЛОСУВАВ"}],"voteTimestamp":"20.10.17 13:03:28"},{"voteName":"За поправку до № 7 від 20.10.17 Про внесення змін в кількісний та персональний склад постійних комісій Дрогобицької міської ради; на голосування п.п. 2.5","namedVoting":[{"1016":"ЗА"},{"1023":"УТРИМАВСЯ"},{"1031":"ЗА"},{"1033":"НЕ ГОЛОСУВАВ"},{"1012":"НЕ ГОЛОСУВАВ"},{"1013":"ЗА"},{"1037":"ЗА"},{"1022":"НЕ ГОЛОСУВАВ"},{"1004":"ЗА"},{"1028":"ЗА"},{"1032":"ЗА"},{"1029":"ВІДСУТНІЙ"},{"1015":"ЗА"},{"1009":"ЗА"},{"1006":"НЕ ГОЛОСУВАВ"},{"1025":"ВІДСУТНІЙ"},{"1030":"ЗА"},{"1034":"ЗА"},{"1017":"ЗА"},{"1035":"ВІДСУТНІЙ"},{"1003":"ЗА"},{"1026":"НЕ ГОЛОСУВАВ"},{"1010":"НЕ ГОЛОСУВАВ"},{"1018":"ВІДСУТНІЙ"},{"1001":"УТРИМАВСЯ"},{"1019":"НЕ ГОЛОСУВАВ"},{"1007":"ЗА"},{"1011":"ЗА"},{"1020":"ПРОТИ"},{"1005":"ЗА"},{"1021":"ПРОТИ"},{"1024":"ЗА"},{"1002":"НЕ ГОЛОСУВАВ"},{"1027":"ЗА"},{"1014":"ЗА"},{"1036":"НЕ ГОЛОСУВАВ"}],"voteTimestamp":"20.10.17 13:04:40"},{"voteName":"За поправку до № 7 від 20.10.17 Про внесення змін в кількісний та персональний склад постійних комісій Дрогобицької міської ради; наголосування п.п. 2.6","namedVoting":[{"1016":"ЗА"},{"1023":"ЗА"},{"1031":"ЗА"},{"1033":"НЕ ГОЛОСУВАВ"},{"1012":"ЗА"},{"1013":"ЗА"},{"1037":"ЗА"},{"1022":"ЗА"},{"1004":"ЗА"},{"1028":"ЗА"},{"1032":"ПРОТИ"},{"1029":"ВІДСУТНІЙ"},{"1015":"ЗА"},{"1009":"ЗА"},{"1006":"ЗА"},{"1025":"ВІДСУТНІЙ"},{"1030":"ЗА"},{"1034":"ЗА"},{"1017":"НЕ ГОЛОСУВАВ"},{"1035":"ВІДСУТНІЙ"},{"1003":"ЗА"},{"1026":"НЕ ГОЛОСУВАВ"},{"1010":"ЗА"},{"1018":"ВІДСУТНІЙ"},{"1001":"ЗА"},{"1019":"НЕ ГОЛОСУВАВ"},{"1007":"НЕ ГОЛОСУВАВ"},{"1011":"НЕ ГОЛОСУВАВ"},{"1020":"ПРОТИ"},{"1005":"ЗА"},{"1021":"ЗА"},{"1024":"ЗА"},{"1002":"ЗА"},{"1027":"НЕ ГОЛОСУВАВ"},{"1014":"ЗА"},{"1036":"НЕ ГОЛОСУВАВ"}],"voteTimestamp":"20.10.17 13:07:09"},{"voteName":"За поправку до № 7 від 20.10.17 Про внесення змін в кількісний та персональний склад постійних комісій Дрогобицької міської ради; доповнити п. 2 п.п. 2.7 Балога включти в комісію з питань оренди","namedVoting":[{"1016":"НЕ ГОЛОСУВАВ"},{"1023":"НЕ ГОЛОСУВАВ"},{"1031":"ПРОТИ"},{"1033":"НЕ ГОЛОСУВАВ"},{"1012":"ЗА"},{"1013":"ПРОТИ"},{"1037":"НЕ ГОЛОСУВАВ"},{"1022":"НЕ ГОЛОСУВАВ"},{"1004":"НЕ ГОЛОСУВАВ"},{"1028":"НЕ ГОЛОСУВАВ"},{"1032":"НЕ ГОЛОСУВАВ"},{"1029":"ВІДСУТНІЙ"},{"1015":"ЗА"},{"1009":"НЕ ГОЛОСУВАВ"},{"1006":"ЗА"},{"1025":"ВІДСУТНІЙ"},{"1030":"ЗА"},{"1034":"ЗА"},{"1017":"ЗА"},{"1035":"ВІДСУТНІЙ"},{"1003":"НЕ ГОЛОСУВАВ"},{"1026":"НЕ ГОЛОСУВАВ"},{"1010":"ЗА"},{"1018":"ВІДСУТНІЙ"},{"1001":"ЗА"},{"1019":"НЕ ГОЛОСУВАВ"},{"1007":"НЕ ГОЛОСУВАВ"},{"1011":"ЗА"},{"1020":"ПРОТИ"},{"1005":"НЕ ГОЛОСУВАВ"},{"1021":"УТРИМАВСЯ"},{"1024":"НЕ ГОЛОСУВАВ"},{"1002":"ЗА"},{"1027":"ЗА"},{"1014":"ЗА"},{"1036":"НЕ ГОЛОСУВАВ"}],"voteTimestamp":"20.10.17 13:08:36"},{"voteName":"За - 21 Проти - 0 Утрималися - 0 Не голосували - 11 Відсутні - 5 Всього - 37","namedVoting":[{"1016":"ЗА"},{"1023":"ЗА"},{"1031":"ЗА"},{"1033":"НЕ ГОЛОСУВАВ"},{"1012":"НЕ ГОЛОСУВАВ"},{"1013":"ЗА"},{"1037":"НЕ ГОЛОСУВАВ"},{"1022":"НЕ ГОЛОСУВАВ"},{"1004":"ЗА"},{"1028":"ЗА"},{"1032":"ЗА"},{"1029":"ВІДСУТНІЙ"},{"1015":"ЗА"},{"1009":"ЗА"},{"1006":"ЗА"},{"1025":"ВІДСУТНІЙ"},{"1030":"ЗА"},{"1034":"ЗА"},{"1017":"ЗА"},{"1035":"ВІДСУТНІЙ"},{"1003":"НЕ ГОЛОСУВАВ"},{"1026":"НЕ ГОЛОСУВАВ"},{"1010":"ЗА"},{"1018":"ВІДСУТНІЙ"},{"1001":"ЗА"},{"1019":"ЗА"},{"1007":"НЕ ГОЛОСУВАВ"},{"1011":"ЗА"},{"1020":"НЕ ГОЛОСУВАВ"},{"1005":"НЕ ГОЛОСУВАВ"},{"1021":"ЗА"},{"1024":"ЗА"},{"1002":"НЕ ГОЛОСУВАВ"},{"1027":"ЗА"},{"1014":"ЗА"},{"1036":"НЕ ГОЛОСУВАВ"}],"voteTimestamp":"20.10.17 13:10:27"},{"voteName":"Про внесення змін в кількісний та персональний склад постійних комісій Дрогобицької міської ради","namedVoting":[{"1016":"ЗА"},{"1023":"ЗА"},{"1031":"ЗА"},{"1033":"НЕ ГОЛОСУВАВ"},{"1012":"НЕ ГОЛОСУВАВ"},{"1013":"НЕ ГОЛОСУВАВ"},{"1037":"ЗА"},{"1022":"НЕ ГОЛОСУВАВ"},{"1004":"ЗА"},{"1028":"ЗА"},{"1032":"ЗА"},{"1029":"ВІДСУТНІЙ"},{"1015":"ЗА"},{"1009":"ЗА"},{"1006":"ЗА"},{"1025":"ВІДСУТНІЙ"},{"1030":"ЗА"},{"1034":"ЗА"},{"1017":"ЗА"},{"1035":"ВІДСУТНІЙ"},{"1003":"ЗА"},{"1026":"НЕ ГОЛОСУВАВ"},{"1010":"ЗА"},{"1018":"ВІДСУТНІЙ"},{"1001":"ЗА"},{"1019":"НЕ ГОЛОСУВАВ"},{"1007":"ЗА"},{"1011":"ЗА"},{"1020":"НЕ ГОЛОСУВАВ"},{"1005":"ЗА"},{"1021":"ЗА"},{"1024":"ЗА"},{"1002":"НЕ ГОЛОСУВАВ"},{"1027":"ЗА"},{"1014":"ЗА"},{"1036":"НЕ ГОЛОСУВАВ"}],"voteTimestamp":"20.10.17 13:11:01"},{"voteName":"Про уповноваження ПАТ «Львівобленерго» на електрифікацію кварталів індивідуальної забудови в районі вул. Северина Наливайка в м. Дрогобичі","namedVoting":[{"1016":"ЗА"},{"1023":"ЗА"},{"1031":"ЗА"},{"1033":"НЕ ГОЛОСУВАВ"},{"1012":"ЗА"},{"1013":"ЗА"},{"1037":"ЗА"},{"1022":"НЕ ГОЛОСУВАВ"},{"1004":"ЗА"},{"1028":"ЗА"},{"1032":"ВІДСУТНІЙ"},{"1029":"НЕ ГОЛОСУВАВ"},{"1015":"ЗА"},{"1009":"ЗА"},{"1006":"ЗА"},{"1025":"ВІДСУТНІЙ"},{"1030":"ЗА"},{"1034":"ЗА"},{"1017":"ЗА"},{"1035":"ВІДСУТНІЙ"},{"1003":"ЗА"},{"1026":"НЕ ГОЛОСУВАВ"},{"1010":"ЗА"},{"1018":"ВІДСУТНІЙ"},{"1001":"ЗА"},{"1019":"ЗА"},{"1007":"ЗА"},{"1011":"ЗА"},{"1020":"ЗА"},{"1005":"ЗА"},{"1021":"ЗА"},{"1024":"ЗА"},{"1002":"ЗА"},{"1027":"ЗА"},{"1014":"ЗА"},{"1036":"НЕ ГОЛОСУВАВ"}],"voteTimestamp":"20.10.17 13:13:28"},{"voteName":"Про будівницво інженерно - транспортної інфраструктури будинків котеджного типу по вул.","namedVoting":[{"1016":"ЗА"},{"1023":"ЗА"},{"1031":"ЗА"},{"1033":"НЕ ГОЛОСУВАВ"},{"1012":"ЗА"},{"1013":"ЗА"},{"1037":"ЗА"},{"1022":"ЗА"},{"1004":"ЗА"},{"1028":"ЗА"},{"1032":"ВІДСУТНІЙ"},{"1029":"ВІДСУТНІЙ"},{"1015":"ЗА"},{"1009":"ЗА"},{"1006":"ЗА"},{"1025":"ВІДСУТНІЙ"},{"1030":"ЗА"},{"1034":"ЗА"},{"1017":"ЗА"},{"1035":"ВІДСУТНІЙ"},{"1003":"ЗА"},{"1026":"НЕ ГОЛОСУВАВ"},{"1010":"ЗА"},{"1018":"ВІДСУТНІЙ"},{"1001":"ЗА"},{"1019":"ЗА"},{"1007":"ЗА"},{"1011":"ЗА"},{"1020":"ЗА"},{"1005":"ЗА"},{"1021":"ЗА"},{"1024":"ЗА"},{"1002":"НЕ ГОЛОСУВАВ"},{"1027":"ЗА"},{"1014":"ЗА"},{"1036":"НЕ ГОЛОСУВАВ"}],"voteTimestamp":"20.10.17 13:17:38"},{"voteName":"Про підтвердження дії рішення Дрогобицької міської ради № 855 від 03.10.2017 «Про надання в оренду земельної ділянки» ","namedVoting":[{"1016":"НЕ ГОЛОСУВАВ"},{"1023":"УТРИМАВСЯ"},{"1031":"ПРОТИ"},{"1033":"НЕ ГОЛОСУВАВ"},{"1012":"ПРОТИ"},{"1013":"НЕ ГОЛОСУВАВ"},{"1037":"ПРОТИ"},{"1022":"НЕ ГОЛОСУВАВ"},{"1004":"НЕ ГОЛОСУВАВ"},{"1028":"НЕ ГОЛОСУВАВ"},{"1032":"ВІДСУТНІЙ"},{"1029":"ВІДСУТНІЙ"},{"1015":"УТРИМАВСЯ"},{"1009":"НЕ ГОЛОСУВАВ"},{"1006":"НЕ ГОЛОСУВАВ"},{"1025":"ВІДСУТНІЙ"},{"1030":"УТРИМАВСЯ"},{"1034":"ПРОТИ"},{"1017":"НЕ ГОЛОСУВАВ"},{"1035":"ВІДСУТНІЙ"},{"1003":"ЗА"},{"1026":"НЕ ГОЛОСУВАВ"},{"1010":"ПРОТИ"},{"1018":"ВІДСУТНІЙ"},{"1001":"УТРИМАВСЯ"},{"1019":"НЕ ГОЛОСУВАВ"},{"1007":"ПРОТИ"},{"1011":"ПРОТИ"},{"1020":"ПРОТИ"},{"1005":"ЗА"},{"1021":"ПРОТИ"},{"1024":"НЕ ГОЛОСУВАВ"},{"1002":"НЕ ГОЛОСУВАВ"},{"1027":"ЗА"},{"1014":"ПРОТИ"},{"1036":"НЕ ГОЛОСУВАВ"}],"voteTimestamp":"20.10.17 13:19:34"},{"voteName":"Про внесення змін в кількісний та персональний склад виконавчого комітету Дрогобицької міської ради","namedVoting":[{"1016":"ЗА"},{"1023":"ЗА"},{"1031":"ЗА"},{"1033":"НЕ ГОЛОСУВАВ"},{"1012":"ЗА"},{"1013":"ЗА"},{"1037":"ЗА"},{"1022":"ЗА"},{"1004":"ЗА"},{"1028":"ЗА"},{"1032":"ВІДСУТНІЙ"},{"1029":"ВІДСУТНІЙ"},{"1015":"ЗА"},{"1009":"ЗА"},{"1006":"ЗА"},{"1025":"ВІДСУТНІЙ"},{"1030":"ЗА"},{"1034":"ЗА"},{"1017":"ЗА"},{"1035":"ВІДСУТНІЙ"},{"1003":"НЕ ГОЛОСУВАВ"},{"1026":"НЕ ГОЛОСУВАВ"},{"1010":"ЗА"},{"1018":"ВІДСУТНІЙ"},{"1001":"ЗА"},{"1019":"ЗА"},{"1007":"ЗА"},{"1011":"ЗА"},{"1020":"ЗА"},{"1005":"ЗА"},{"1021":"ЗА"},{"1024":"ЗА"},{"1002":"НЕ ГОЛОСУВАВ"},{"1027":"ЗА"},{"1014":"ЗА"},{"1036":"НЕ ГОЛОСУВАВ"}],"voteTimestamp":"20.10.17 13:20:40"},{"voteName":"Про скасування п. 3 рішення виконавчого комітету Дрогобицької міської ради від 24 квітня 2014 р. № 43 Про встановлення дорожніх знаків на вулицях.","namedVoting":[{"1016":"НЕ ГОЛОСУВАВ"},{"1023":"ЗА"},{"1031":"ЗА"},{"1033":"НЕ ГОЛОСУВАВ"},{"1012":"ЗА"},{"1013":"НЕ ГОЛОСУВАВ"},{"1037":"ЗА"},{"1022":"ЗА"},{"1004":"НЕ ГОЛОСУВАВ"},{"1028":"НЕ ГОЛОСУВАВ"},{"1032":"ВІДСУТНІЙ"},{"1029":"ВІДСУТНІЙ"},{"1015":"ЗА"},{"1009":"НЕ ГОЛОСУВАВ"},{"1006":"ЗА"},{"1025":"ВІДСУТНІЙ"},{"1030":"ЗА"},{"1034":"ЗА"},{"1017":"НЕ ГОЛОСУВАВ"},{"1035":"ВІДСУТНІЙ"},{"1003":"НЕ ГОЛОСУВАВ"},{"1026":"НЕ ГОЛОСУВАВ"},{"1010":"ЗА"},{"1018":"ВІДСУТНІЙ"},{"1001":"ЗА"},{"1019":"НЕ ГОЛОСУВАВ"},{"1007":"УТРИМАВСЯ"},{"1011":"ЗА"},{"1020":"ЗА"},{"1005":"НЕ ГОЛОСУВАВ"},{"1021":"НЕ ГОЛОСУВАВ"},{"1024":"ЗА"},{"1002":"ЗА"},{"1027":"ЗА"},{"1014":"ЗА"},{"1036":"НЕ ГОЛОСУВАВ"}],"voteTimestamp":"20.10.17 13:21:38"}]}